{
  "status": "ready",
  "licensePreference": "cc0-or-attribution",
  "batchCommand": "node Tools/freesound.cjs batch Ester/Audio/freesound-plan.json",
  "downloadCommandTemplate": "node Tools/freesound.cjs pick \"${query}\" --index 0 --out ${out} --duration-max ${durationMax} --license cc0-or-attribution --preview preview-hq-mp3",
  "items": [
    { "out": "Ester/Audio/UI/ui_tap_soft", "query": "soft shell click underwater", "fallbackQueries": ["soft click", "button click"], "durationMax": 0.5 },
    { "out": "Ester/Audio/UI/ui_confirm_chime", "query": "soft water chime", "fallbackQueries": ["water chime", "tiny chime"], "durationMax": 0.9 },
    { "out": "Ester/Audio/UI/ui_reject_soft", "query": "muted soft thud water", "fallbackQueries": ["soft thud", "cancel button sound"], "durationMax": 0.7 },
    { "out": "Ester/Audio/UI/ui_panel_open", "query": "short water whoosh gentle", "fallbackQueries": ["water whoosh", "water swish"], "durationMax": 1.0 },
    { "out": "Ester/Audio/UI/ui_panel_close", "query": "soft water swish close", "fallbackQueries": ["water swish", "water whoosh"], "durationMax": 1.0 },
    { "out": "Ester/Audio/UI/ui_upgrade_buy", "query": "shell chime sparkle", "fallbackQueries": ["water chime", "tiny chime"], "durationMax": 1.0 },
    { "out": "Ester/Audio/UI/ui_upgrade_fail", "query": "soft deny click muted", "fallbackQueries": ["soft thud", "cancel button sound"], "durationMax": 0.7 },
    { "out": "Ester/Audio/UI/world_tap_accept", "query": "small water ripple tap", "fallbackQueries": ["water ripple", "water drop"], "durationMax": 0.7 },
    { "out": "Ester/Audio/UI/world_tap_reject", "query": "low water ripple thud", "fallbackQueries": ["soft thud", "low thud"], "durationMax": 0.8 },
    { "out": "Ester/Audio/Mermaid/mermaid_eat_soft", "query": "underwater nibble bubble pop", "fallbackQueries": ["bite", "chew"], "index": 3, "durationMax": 0.9 },
    { "out": "Ester/Audio/Mermaid/mermaid_fish_play", "query": "playful underwater bubbles", "fallbackQueries": ["underwater bubbles", "bubbles"], "durationMax": 1.2 },
    { "out": "Ester/Audio/Mermaid/mermaid_scared_swish", "query": "quick underwater swish", "fallbackQueries": ["water swish", "whoosh"], "durationMax": 1.0 },
    { "out": "Ester/Audio/Mermaid/mermaid_rest_sigh", "query": "soft underwater breath bubble", "fallbackQueries": ["underwater bubbles", "soft breath"], "durationMax": 1.2 },
    { "out": "Ester/Audio/Progression/egg_tap_warm", "query": "soft glass tap warm", "fallbackQueries": ["glass tap", "glass hit"], "durationMax": 0.7 },
    { "out": "Ester/Audio/Progression/egg_crack_soft", "query": "delicate eggshell crack", "fallbackQueries": ["eggshell crack", "crack"], "durationMax": 0.8 },
    { "out": "Ester/Audio/Progression/hatch_birth_shimmer", "query": "magical shimmer water birth", "fallbackQueries": ["shimmer", "magic shimmer"], "durationMax": 2.0 },
    { "out": "Ester/Audio/Progression/evolution_shimmer", "query": "magical underwater shimmer", "fallbackQueries": ["shimmer", "magic shimmer"], "durationMax": 2.0 },
    { "out": "Ester/Audio/World/food_rare_shimmer", "query": "small magic shimmer underwater", "fallbackQueries": ["shimmer", "magic shimmer"], "durationMax": 1.2 },
    { "out": "Ester/Audio/World/pearl_reward_chime", "query": "pearl shell chime", "fallbackQueries": ["water chime", "tiny chime"], "durationMax": 1.0 },
    { "out": "Ester/Audio/World/depth_record_low_chime", "query": "low soft discovery chime", "fallbackQueries": ["low chime", "water chime"], "durationMax": 1.3 },
    { "out": "Ester/Audio/World/zone_unlock_wave", "query": "large underwater wave whoosh", "fallbackQueries": ["water whoosh", "whoosh"], "durationMax": 2.0 },
    { "out": "Ester/Audio/World/region_discover_chime", "query": "soft discovery sparkle chime", "fallbackQueries": ["water chime", "shimmer"], "durationMax": 1.4 },
    { "out": "Ester/Audio/World/travel_start_current", "query": "underwater current start", "fallbackQueries": ["water whoosh", "water swish"], "durationMax": 1.5 },
    { "out": "Ester/Audio/World/travel_arrive_chime", "query": "gentle arrival chime", "fallbackQueries": ["water chime", "tiny chime"], "durationMax": 1.2 },
    { "out": "Ester/Audio/World/bubble_burst_cluster", "query": "underwater bubble burst cluster", "fallbackQueries": ["underwater bubbles", "bubbles"], "durationMax": 1.2 },
    { "out": "Ester/Audio/World/current_rush_short", "query": "underwater current rush", "fallbackQueries": ["water whoosh", "water swish"], "durationMax": 2.4 },
    { "out": "Ester/Audio/World/rare_fish_pass", "query": "fast fish swim by underwater", "fallbackQueries": ["water swish", "whoosh"], "durationMax": 1.2 },
    { "out": "Ester/Audio/World/big_shadow_rumble", "query": "deep underwater rumble short", "fallbackQueries": ["deep rumble", "low rumble"], "durationMax": 2.5 },
    { "out": "Ester/Audio/World/boat_muffled_pass", "query": "muffled boat underwater pass", "fallbackQueries": ["motor boat", "boat"], "durationMax": 3.5 },
    { "out": "Ester/Audio/World/falling_object_splash", "query": "small object splash underwater", "fallbackQueries": ["small splash", "water splash"], "durationMax": 1.5 },
    { "out": "Ester/Audio/Refuge/refuge_portal_open", "query": "magic portal water vortex", "fallbackQueries": ["portal whoosh", "portal"], "durationMax": 2.0 },
    { "out": "Ester/Audio/Refuge/refuge_portal_enter", "query": "soft portal whoosh water", "fallbackQueries": ["portal whoosh", "water whoosh"], "durationMax": 1.5 },
    { "out": "Ester/Audio/Minigames/tide_select_shell", "query": "tiny shell click", "fallbackQueries": ["soft click", "button click"], "durationMax": 0.4 },
    { "out": "Ester/Audio/Minigames/tide_swap_water", "query": "short water slide swish", "fallbackQueries": ["water swish", "water whoosh"], "durationMax": 0.5 },
    { "out": "Ester/Audio/Minigames/tide_invalid_soft", "query": "soft invalid click muted", "fallbackQueries": ["soft thud", "cancel button sound"], "durationMax": 0.5 },
    { "out": "Ester/Audio/Minigames/tide_match_pop", "query": "bubble pop game match", "fallbackQueries": ["water pop", "bubble pop"], "durationMax": 0.8 },
    { "out": "Ester/Audio/Minigames/tide_cascade_chime", "query": "bubble pop cluster game", "fallbackQueries": ["water pop bubble game", "short water splash bubble"], "durationMax": 1.4 },
    { "out": "Ester/Audio/Minigames/tide_goal_complete", "query": "water pop bubble game", "fallbackQueries": ["short water splash bubble", "bubble pop cluster game"], "durationMax": 1.4 },
    { "out": "Ester/Audio/Minigames/challenge_open", "query": "soft magical whoosh open", "fallbackQueries": ["portal whoosh", "water whoosh"], "durationMax": 1.1 },
    { "out": "Ester/Audio/Minigames/challenge_success", "query": "short water splash bubble", "fallbackQueries": ["water pop bubble game", "bubble pop cluster game"], "durationMax": 1.4 },
    { "out": "Ester/Audio/Minigames/challenge_fail_soft", "query": "soft fail gentle", "fallbackQueries": ["soft thud", "cancel button sound"], "durationMax": 1.1 },
    { "out": "Ester/Audio/Minigames/climb_start_bubble", "query": "bubble lift start", "fallbackQueries": ["underwater bubbles", "bubbles"], "durationMax": 1.0 },
    { "out": "Ester/Audio/Minigames/climb_land_bubble", "query": "soft bubble contact", "fallbackQueries": ["water drop", "water pop"], "durationMax": 0.6 },
    { "out": "Ester/Audio/Minigames/climb_bounce_pop", "query": "bubble bounce pop", "fallbackQueries": ["water pop", "bubble pop"], "durationMax": 0.7 },
    { "out": "Ester/Audio/Minigames/climb_platform_pop", "query": "small bubble pop cluster", "fallbackQueries": ["water pop", "bubble pop"], "durationMax": 0.8 },
    { "out": "Ester/Audio/Minigames/climb_goal_complete", "query": "water pop bubble game", "fallbackQueries": ["short water splash bubble", "bubble pop cluster game"], "index": 1, "durationMax": 1.4 },
    { "out": "Ester/Audio/Ambience/ambient_clear_water", "query": "ocean ambience", "fallbackQueries": ["underwater ambience"], "durationMax": 45 },
    { "out": "Ester/Audio/Ambience/ambient_shallow_reef", "query": "underwater ambience", "fallbackQueries": ["water ambience"], "index": 3, "durationMax": 45 },
    { "out": "Ester/Audio/Ambience/ambient_mid_water", "query": "deep sea ambience", "fallbackQueries": ["underwater ambience"], "index": 2, "durationMax": 45 },
    { "out": "Ester/Audio/Ambience/ambient_deep_sea", "query": "deep sea ambience", "fallbackQueries": ["underwater ambience"], "index": 1, "durationMax": 45 },
    { "out": "Ester/Audio/Ambience/ambient_abyss_hum", "query": "ocean ambience", "fallbackQueries": ["deep sea ambience"], "index": 1, "durationMax": 45 },
    { "out": "Ester/Audio/Ambience/ambient_refuge_soft", "query": "magic ambience", "fallbackQueries": ["soft ambience"], "index": 2, "durationMax": 45 }
  ]
}
