{"nodes": [{"id": "private_tmp_mer_game_worldchunkfactory_swift", "label": "WorldChunkFactory.swift", "file_type": "code", "source_file": "Game/WorldChunkFactory.swift", "source_location": "L1"}, {"id": "foundation", "label": "Foundation", "file_type": "code", "type": "module", "source_file": "Game/WorldChunkFactory.swift", "source_location": "L8"}, {"id": "spritekit", "label": "SpriteKit", "file_type": "code", "type": "module", "source_file": "Game/WorldChunkFactory.swift", "source_location": "L9"}, {"id": "private_tmp_mer_game_worldchunkfactory_worldchunkfactory", "label": "WorldChunkFactory", "file_type": "code", "source_file": "Game/WorldChunkFactory.swift", "source_location": "L11", "_callable": true}, {"id": "private_tmp_mer_game_worldchunkfactory_reefcluster", "label": "ReefCluster", "file_type": "code", "source_file": "Game/WorldChunkFactory.swift", "source_location": "L12", "_callable": true}, {"id": "sknode", "label": "SKNode", "file_type": "code", "source_file": "", "source_location": "", "origin_file": "/private/tmp/mer/Game/WorldChunkFactory.swift"}, {"id": "cgsize", "label": "CGSize", "file_type": "code", "source_file": "", "source_location": "", "origin_file": "/private/tmp/mer/Game/WorldChunkFactory.swift"}, {"id": "private_tmp_mer_game_worldchunkfactory_placedreefcluster", "label": "PlacedReefCluster", "file_type": "code", "source_file": "Game/WorldChunkFactory.swift", "source_location": "L17", "_callable": true}, {"id": "cgpoint", "label": "CGPoint", "file_type": "code", "source_file": "", "source_location": "", "origin_file": "/private/tmp/mer/Game/WorldChunkFactory.swift"}, {"id": "cgfloat", "label": "CGFloat", "file_type": "code", "source_file": "", "source_location": "", "origin_file": "/private/tmp/mer/Game/WorldChunkFactory.swift"}, {"id": "private_tmp_mer_game_worldchunkfactory_worldchunkfactory_makechunk", "label": ".makeChunk()", "file_type": "code", "source_file": "Game/WorldChunkFactory.swift", "source_location": "L23", "_callable": true}, {"id": "worldchunkcoord", "label": "WorldChunkCoord", "file_type": "code", "source_file": "", "source_location": "", "origin_file": "/private/tmp/mer/Game/WorldChunkFactory.swift"}, {"id": "ecosystembiomeprofile", "label": "EcosystemBiomeProfile", "file_type": "code", "source_file": "", "source_location": "", "origin_file": "/private/tmp/mer/Game/WorldChunkFactory.swift"}, {"id": "private_tmp_mer_game_worldchunkfactory_worldchunkfactory_makeproceduralchunk", "label": ".makeProceduralChunk()", "file_type": "code", "source_file": "Game/WorldChunkFactory.swift", "source_location": "L31", "_callable": true}, {"id": "bool", "label": "Bool", "file_type": "code", "source_file": "", "source_location": "", "origin_file": "/private/tmp/mer/Game/WorldChunkFactory.swift"}, {"id": "private_tmp_mer_game_worldchunkfactory_worldchunkfactory_addmacroforms", "label": ".addMacroforms()", "file_type": "code", "source_file": "Game/WorldChunkFactory.swift", "source_location": "L49", "_callable": true}, {"id": "depthzone", "label": "DepthZone", "file_type": "code", "source_file": "", "source_location": "", "origin_file": "/private/tmp/mer/Game/WorldChunkFactory.swift"}, {"id": "aquaticbiome", "label": "AquaticBiome", "file_type": "code", "source_file": "", "source_location": "", "origin_file": "/private/tmp/mer/Game/WorldChunkFactory.swift"}, {"id": "private_tmp_mer_game_worldchunkfactory_worldchunkfactory_addcurrents", "label": ".addCurrents()", "file_type": "code", "source_file": "Game/WorldChunkFactory.swift", "source_location": "L83", "_callable": true}, {"id": "private_tmp_mer_game_worldchunkfactory_worldchunkfactory_addreefs", "label": ".addReefs()", "file_type": "code", "source_file": "Game/WorldChunkFactory.swift", "source_location": "L109", "_callable": true}, {"id": "private_tmp_mer_game_worldchunkfactory_worldchunkfactory_reefclusterposition", "label": ".reefClusterPosition()", "file_type": "code", "source_file": "Game/WorldChunkFactory.swift", "source_location": "L151", "_callable": true}, {"id": "cgrect", "label": "CGRect", "file_type": "code", "source_file": "", "source_location": "", "origin_file": "/private/tmp/mer/Game/WorldChunkFactory.swift"}, {"id": "seededgenerator", "label": "SeededGenerator", "file_type": "code", "source_file": "", "source_location": "", "origin_file": "/private/tmp/mer/Game/WorldChunkFactory.swift"}, {"id": "private_tmp_mer_game_worldchunkfactory_worldchunkfactory_hasverticalconflict", "label": ".hasVerticalConflict()", "file_type": "code", "source_file": "Game/WorldChunkFactory.swift", "source_location": "L175", "_callable": true}, {"id": "private_tmp_mer_game_worldchunkfactory_worldchunkfactory_reefclusterzposition", "label": ".reefClusterZPosition()", "file_type": "code", "source_file": "Game/WorldChunkFactory.swift", "source_location": "L190", "_callable": true}, {"id": "private_tmp_mer_game_worldchunkfactory_worldchunkfactory_addambientemitters", "label": ".addAmbientEmitters()", "file_type": "code", "source_file": "Game/WorldChunkFactory.swift", "source_location": "L197", "_callable": true}, {"id": "private_tmp_mer_game_worldchunkfactory_worldchunkfactory_makereefcluster", "label": ".makeReefCluster()", "file_type": "code", "source_file": "Game/WorldChunkFactory.swift", "source_location": "L226", "_callable": true}, {"id": "private_tmp_mer_game_worldchunkfactory_worldchunkfactory_makerocksprite", "label": ".makeRockSprite()", "file_type": "code", "source_file": "Game/WorldChunkFactory.swift", "source_location": "L316", "_callable": true}, {"id": "skspritenode", "label": "SKSpriteNode", "file_type": "code", "source_file": "", "source_location": "", "origin_file": "/private/tmp/mer/Game/WorldChunkFactory.swift"}, {"id": "private_tmp_mer_game_worldchunkfactory_worldchunkfactory_makereefskirtsprite", "label": ".makeReefSkirtSprite()", "file_type": "code", "source_file": "Game/WorldChunkFactory.swift", "source_location": "L330", "_callable": true}, {"id": "private_tmp_mer_game_worldchunkfactory_worldchunkfactory_makekelpsprite", "label": ".makeKelpSprite()", "file_type": "code", "source_file": "Game/WorldChunkFactory.swift", "source_location": "L347", "_callable": true}, {"id": "worldstampkind", "label": "WorldStampKind", "file_type": "code", "source_file": "", "source_location": "", "origin_file": "/private/tmp/mer/Game/WorldChunkFactory.swift"}, {"id": "private_tmp_mer_game_worldchunkfactory_worldchunkfactory_makedetailsprite", "label": ".makeDetailSprite()", "file_type": "code", "source_file": "Game/WorldChunkFactory.swift", "source_location": "L389", "_callable": true}, {"id": "private_tmp_mer_game_worldchunkfactory_worldchunkfactory_makeplantsprite", "label": ".makePlantSprite()", "file_type": "code", "source_file": "Game/WorldChunkFactory.swift", "source_location": "L411", "_callable": true}, {"id": "ecosystemvegetationrule", "label": "EcosystemVegetationRule", "file_type": "code", "source_file": "", "source_location": "", "origin_file": "/private/tmp/mer/Game/WorldChunkFactory.swift"}, {"id": "private_tmp_mer_game_worldchunkfactory_worldchunkfactory_fitplantsprite", "label": ".fitPlantSprite()", "file_type": "code", "source_file": "Game/WorldChunkFactory.swift", "source_location": "L439", "_callable": true}, {"id": "private_tmp_mer_game_worldchunkfactory_worldchunkfactory_plantingx", "label": ".plantingX()", "file_type": "code", "source_file": "Game/WorldChunkFactory.swift", "source_location": "L473", "_callable": true}, {"id": "private_tmp_mer_game_worldchunkfactory_worldchunkfactory_plantingsurfacey", "label": ".plantingSurfaceY()", "file_type": "code", "source_file": "Game/WorldChunkFactory.swift", "source_location": "L485", "_callable": true}, {"id": "private_tmp_mer_game_worldchunkfactory_worldchunkfactory_rootsink", "label": ".rootSink()", "file_type": "code", "source_file": "Game/WorldChunkFactory.swift", "source_location": "L497", "_callable": true}, {"id": "private_tmp_mer_game_worldchunkfactory_worldchunkfactory_rootanchory", "label": ".rootAnchorY()", "file_type": "code", "source_file": "Game/WorldChunkFactory.swift", "source_location": "L502", "_callable": true}, {"id": "private_tmp_mer_game_worldchunkfactory_worldchunkfactory_detailsize", "label": ".detailSize()", "file_type": "code", "source_file": "Game/WorldChunkFactory.swift", "source_location": "L525", "_callable": true}, {"id": "private_tmp_mer_game_worldchunkfactory_worldchunkfactory_reefdensity", "label": ".reefDensity()", "file_type": "code", "source_file": "Game/WorldChunkFactory.swift", "source_location": "L558", "_callable": true}, {"id": "private_tmp_mer_game_worldchunkfactory_worldchunkfactory_randompoint", "label": ".randomPoint()", "file_type": "code", "source_file": "Game/WorldChunkFactory.swift", "source_location": "L597", "_callable": true}], "edges": [{"source": "private_tmp_mer_game_worldchunkfactory_swift", "target": "foundation", "relation": "imports", "context": "import", "confidence": "EXTRACTED", "source_file": "Game/WorldChunkFactory.swift", "source_location": "L8", "weight": 1.0}, {"source": "private_tmp_mer_game_worldchunkfactory_swift", "target": "spritekit", "relation": "imports", "context": "import", "confidence": "EXTRACTED", "source_file": "Game/WorldChunkFactory.swift", "source_location": "L9", "weight": 1.0}, {"source": "private_tmp_mer_game_worldchunkfactory_swift", "target": "private_tmp_mer_game_worldchunkfactory_worldchunkfactory", "relation": "contains", "confidence": "EXTRACTED", "source_file": "Game/WorldChunkFactory.swift", "source_location": "L11", "weight": 1.0}, {"source": "private_tmp_mer_game_worldchunkfactory_swift", "target": "private_tmp_mer_game_worldchunkfactory_reefcluster", "relation": "contains", "confidence": "EXTRACTED", "source_file": "Game/WorldChunkFactory.swift", "source_location": "L12", "weight": 1.0}, {"source": "private_tmp_mer_game_worldchunkfactory_reefcluster", "target": "sknode", "relation": "references", "confidence": "EXTRACTED", "source_file": "Game/WorldChunkFactory.swift", "source_location": "L13", "weight": 1.0, "context": "field"}, {"source": "private_tmp_mer_game_worldchunkfactory_reefcluster", "target": "cgsize", "relation": "references", "confidence": "EXTRACTED", "source_file": "Game/WorldChunkFactory.swift", "source_location": "L14", "weight": 1.0, "context": "field"}, {"source": "private_tmp_mer_game_worldchunkfactory_swift", "target": "private_tmp_mer_game_worldchunkfactory_placedreefcluster", "relation": "contains", "confidence": "EXTRACTED", "source_file": "Game/WorldChunkFactory.swift", "source_location": "L17", "weight": 1.0}, {"source": "private_tmp_mer_game_worldchunkfactory_placedreefcluster", "target": "cgpoint", "relation": "references", "confidence": "EXTRACTED", "source_file": "Game/WorldChunkFactory.swift", "source_location": "L18", "weight": 1.0, "context": "field"}, {"source": "private_tmp_mer_game_worldchunkfactory_placedreefcluster", "target": "cgsize", "relation": "references", "confidence": "EXTRACTED", "source_file": "Game/WorldChunkFactory.swift", "source_location": "L19", "weight": 1.0, "context": "field"}, {"source": "private_tmp_mer_game_worldchunkfactory_placedreefcluster", "target": "cgfloat", "relation": "references", "confidence": "EXTRACTED", "source_file": "Game/WorldChunkFactory.swift", "source_location": "L20", "weight": 1.0, "context": "field"}, {"source": "private_tmp_mer_game_worldchunkfactory_worldchunkfactory", "target": "private_tmp_mer_game_worldchunkfactory_worldchunkfactory_makechunk", "relation": "method", "confidence": "EXTRACTED", "source_file": "Game/WorldChunkFactory.swift", "source_location": "L23", "weight": 1.0}, {"source": "private_tmp_mer_game_worldchunkfactory_worldchunkfactory_makechunk", "target": "worldchunkcoord", "relation": "references", "confidence": "EXTRACTED", "source_file": "Game/WorldChunkFactory.swift", "source_location": "L23", "weight": 1.0, "context": "parameter_type"}, {"source": "private_tmp_mer_game_worldchunkfactory_worldchunkfactory_makechunk", "target": "ecosystembiomeprofile", "relation": "references", "confidence": "EXTRACTED", "source_file": "Game/WorldChunkFactory.swift", "source_location": "L23", "weight": 1.0, "context": "parameter_type"}, {"source": "private_tmp_mer_game_worldchunkfactory_worldchunkfactory_makechunk", "target": "sknode", "relation": "references", "confidence": "EXTRACTED", "source_file": "Game/WorldChunkFactory.swift", "source_location": "L23", "weight": 1.0, "context": "return_type"}, {"source": "private_tmp_mer_game_worldchunkfactory_worldchunkfactory", "target": "private_tmp_mer_game_worldchunkfactory_worldchunkfactory_makeproceduralchunk", "relation": "method", "confidence": "EXTRACTED", "source_file": "Game/WorldChunkFactory.swift", "source_location": "L31", "weight": 1.0}, {"source": "private_tmp_mer_game_worldchunkfactory_worldchunkfactory_makeproceduralchunk", "target": "worldchunkcoord", "relation": "references", "confidence": "EXTRACTED", "source_file": "Game/WorldChunkFactory.swift", "source_location": "L31", "weight": 1.0, "context": "parameter_type"}, {"source": "private_tmp_mer_game_worldchunkfactory_worldchunkfactory_makeproceduralchunk", "target": "bool", "relation": "references", "confidence": "EXTRACTED", "source_file": "Game/WorldChunkFactory.swift", "source_location": "L31", "weight": 1.0, "context": "parameter_type"}, {"source": "private_tmp_mer_game_worldchunkfactory_worldchunkfactory_makeproceduralchunk", "target": "ecosystembiomeprofile", "relation": "references", "confidence": "EXTRACTED", "source_file": "Game/WorldChunkFactory.swift", "source_location": "L31", "weight": 1.0, "context": "parameter_type"}, {"source": "private_tmp_mer_game_worldchunkfactory_worldchunkfactory_makeproceduralchunk", "target": "sknode", "relation": "references", "confidence": "EXTRACTED", "source_file": "Game/WorldChunkFactory.swift", "source_location": "L31", "weight": 1.0, "context": "return_type"}, {"source": "private_tmp_mer_game_worldchunkfactory_worldchunkfactory", "target": "private_tmp_mer_game_worldchunkfactory_worldchunkfactory_addmacroforms", "relation": "method", "confidence": "EXTRACTED", "source_file": "Game/WorldChunkFactory.swift", "source_location": "L49", "weight": 1.0}, {"source": "private_tmp_mer_game_worldchunkfactory_worldchunkfactory_addmacroforms", "target": "sknode", "relation": "references", "confidence": "EXTRACTED", "source_file": "Game/WorldChunkFactory.swift", "source_location": "L49", "weight": 1.0, "context": "parameter_type"}, {"source": "private_tmp_mer_game_worldchunkfactory_worldchunkfactory_addmacroforms", "target": "worldchunkcoord", "relation": "references", "confidence": "EXTRACTED", "source_file": "Game/WorldChunkFactory.swift", "source_location": "L49", "weight": 1.0, "context": "parameter_type"}, {"source": "private_tmp_mer_game_worldchunkfactory_worldchunkfactory_addmacroforms", "target": "depthzone", "relation": "references", "confidence": "EXTRACTED", "source_file": "Game/WorldChunkFactory.swift", "source_location": "L49", "weight": 1.0, "context": "parameter_type"}, {"source": "private_tmp_mer_game_worldchunkfactory_worldchunkfactory_addmacroforms", "target": "aquaticbiome", "relation": "references", "confidence": "EXTRACTED", "source_file": "Game/WorldChunkFactory.swift", "source_location": "L49", "weight": 1.0, "context": "parameter_type"}, {"source": "private_tmp_mer_game_worldchunkfactory_worldchunkfactory", "target": "private_tmp_mer_game_worldchunkfactory_worldchunkfactory_addcurrents", "relation": "method", "confidence": "EXTRACTED", "source_file": "Game/WorldChunkFactory.swift", "source_location": "L83", "weight": 1.0}, {"source": "private_tmp_mer_game_worldchunkfactory_worldchunkfactory_addcurrents", "target": "sknode", "relation": "references", "confidence": "EXTRACTED", "source_file": "Game/WorldChunkFactory.swift", "source_location": "L83", "weight": 1.0, "context": "parameter_type"}, {"source": "private_tmp_mer_game_worldchunkfactory_worldchunkfactory_addcurrents", "target": "worldchunkcoord", "relation": "references", "confidence": "EXTRACTED", "source_file": "Game/WorldChunkFactory.swift", "source_location": "L83", "weight": 1.0, "context": "parameter_type"}, {"source": "private_tmp_mer_game_worldchunkfactory_worldchunkfactory_addcurrents", "target": "depthzone", "relation": "references", "confidence": "EXTRACTED", "source_file": "Game/WorldChunkFactory.swift", "source_location": "L83", "weight": 1.0, "context": "parameter_type"}, {"source": "private_tmp_mer_game_worldchunkfactory_worldchunkfactory_addcurrents", "target": "aquaticbiome", "relation": "references", "confidence": "EXTRACTED", "source_file": "Game/WorldChunkFactory.swift", "source_location": "L83", "weight": 1.0, "context": "parameter_type"}, {"source": "private_tmp_mer_game_worldchunkfactory_worldchunkfactory", "target": "private_tmp_mer_game_worldchunkfactory_worldchunkfactory_addreefs", "relation": "method", "confidence": "EXTRACTED", "source_file": "Game/WorldChunkFactory.swift", "source_location": "L109", "weight": 1.0}, {"source": "private_tmp_mer_game_worldchunkfactory_worldchunkfactory_addreefs", "target": "sknode", "relation": "references", "confidence": "EXTRACTED", "source_file": "Game/WorldChunkFactory.swift", "source_location": "L109", "weight": 1.0, "context": "parameter_type"}, {"source": "private_tmp_mer_game_worldchunkfactory_worldchunkfactory_addreefs", "target": "worldchunkcoord", "relation": "references", "confidence": "EXTRACTED", "source_file": "Game/WorldChunkFactory.swift", "source_location": "L109", "weight": 1.0, "context": "parameter_type"}, {"source": "private_tmp_mer_game_worldchunkfactory_worldchunkfactory_addreefs", "target": "depthzone", "relation": "references", "confidence": "EXTRACTED", "source_file": "Game/WorldChunkFactory.swift", "source_location": "L109", "weight": 1.0, "context": "parameter_type"}, {"source": "private_tmp_mer_game_worldchunkfactory_worldchunkfactory_addreefs", "target": "aquaticbiome", "relation": "references", "confidence": "EXTRACTED", "source_file": "Game/WorldChunkFactory.swift", "source_location": "L109", "weight": 1.0, "context": "parameter_type"}, {"source": "private_tmp_mer_game_worldchunkfactory_worldchunkfactory_addreefs", "target": "ecosystembiomeprofile", "relation": "references", "confidence": "EXTRACTED", "source_file": "Game/WorldChunkFactory.swift", "source_location": "L109", "weight": 1.0, "context": "parameter_type"}, {"source": "private_tmp_mer_game_worldchunkfactory_worldchunkfactory", "target": "private_tmp_mer_game_worldchunkfactory_worldchunkfactory_reefclusterposition", "relation": "method", "confidence": "EXTRACTED", "source_file": "Game/WorldChunkFactory.swift", "source_location": "L151", "weight": 1.0}, {"source": "private_tmp_mer_game_worldchunkfactory_worldchunkfactory_reefclusterposition", "target": "private_tmp_mer_game_worldchunkfactory_reefcluster", "relation": "references", "confidence": "EXTRACTED", "source_file": "Game/WorldChunkFactory.swift", "source_location": "L151", "weight": 1.0, "context": "parameter_type"}, {"source": "private_tmp_mer_game_worldchunkfactory_worldchunkfactory_reefclusterposition", "target": "cgfloat", "relation": "references", "confidence": "EXTRACTED", "source_file": "Game/WorldChunkFactory.swift", "source_location": "L151", "weight": 1.0, "context": "parameter_type"}, {"source": "private_tmp_mer_game_worldchunkfactory_worldchunkfactory_reefclusterposition", "target": "cgrect", "relation": "references", "confidence": "EXTRACTED", "source_file": "Game/WorldChunkFactory.swift", "source_location": "L151", "weight": 1.0, "context": "parameter_type"}, {"source": "private_tmp_mer_game_worldchunkfactory_worldchunkfactory_reefclusterposition", "target": "private_tmp_mer_game_worldchunkfactory_placedreefcluster", "relation": "references", "confidence": "EXTRACTED", "source_file": "Game/WorldChunkFactory.swift", "source_location": "L151", "weight": 1.0, "context": "parameter_type"}, {"source": "private_tmp_mer_game_worldchunkfactory_worldchunkfactory_reefclusterposition", "target": "seededgenerator", "relation": "references", "confidence": "EXTRACTED", "source_file": "Game/WorldChunkFactory.swift", "source_location": "L151", "weight": 1.0, "context": "parameter_type"}, {"source": "private_tmp_mer_game_worldchunkfactory_worldchunkfactory_reefclusterposition", "target": "cgpoint", "relation": "references", "confidence": "EXTRACTED", "source_file": "Game/WorldChunkFactory.swift", "source_location": "L151", "weight": 1.0, "context": "return_type"}, {"source": "private_tmp_mer_game_worldchunkfactory_worldchunkfactory", "target": "private_tmp_mer_game_worldchunkfactory_worldchunkfactory_hasverticalconflict", "relation": "method", "confidence": "EXTRACTED", "source_file": "Game/WorldChunkFactory.swift", "source_location": "L175", "weight": 1.0}, {"source": "private_tmp_mer_game_worldchunkfactory_worldchunkfactory_hasverticalconflict", "target": "cgpoint", "relation": "references", "confidence": "EXTRACTED", "source_file": "Game/WorldChunkFactory.swift", "source_location": "L175", "weight": 1.0, "context": "parameter_type"}, {"source": "private_tmp_mer_game_worldchunkfactory_worldchunkfactory_hasverticalconflict", "target": "cgsize", "relation": "references", "confidence": "EXTRACTED", "source_file": "Game/WorldChunkFactory.swift", "source_location": "L175", "weight": 1.0, "context": "parameter_type"}, {"source": "private_tmp_mer_game_worldchunkfactory_worldchunkfactory_hasverticalconflict", "target": "cgfloat", "relation": "references", "confidence": "EXTRACTED", "source_file": "Game/WorldChunkFactory.swift", "source_location": "L175", "weight": 1.0, "context": "parameter_type"}, {"source": "private_tmp_mer_game_worldchunkfactory_worldchunkfactory_hasverticalconflict", "target": "private_tmp_mer_game_worldchunkfactory_placedreefcluster", "relation": "references", "confidence": "EXTRACTED", "source_file": "Game/WorldChunkFactory.swift", "source_location": "L175", "weight": 1.0, "context": "parameter_type"}, {"source": "private_tmp_mer_game_worldchunkfactory_worldchunkfactory_hasverticalconflict", "target": "bool", "relation": "references", "confidence": "EXTRACTED", "source_file": "Game/WorldChunkFactory.swift", "source_location": "L175", "weight": 1.0, "context": "return_type"}, {"source": "private_tmp_mer_game_worldchunkfactory_worldchunkfactory", "target": "private_tmp_mer_game_worldchunkfactory_worldchunkfactory_reefclusterzposition", "relation": "method", "confidence": "EXTRACTED", "source_file": "Game/WorldChunkFactory.swift", "source_location": "L190", "weight": 1.0}, {"source": "private_tmp_mer_game_worldchunkfactory_worldchunkfactory_reefclusterzposition", "target": "cgpoint", "relation": "references", "confidence": "EXTRACTED", "source_file": "Game/WorldChunkFactory.swift", "source_location": "L190", "weight": 1.0, "context": "parameter_type"}, {"source": "private_tmp_mer_game_worldchunkfactory_worldchunkfactory_reefclusterzposition", "target": "cgrect", "relation": "references", "confidence": "EXTRACTED", "source_file": "Game/WorldChunkFactory.swift", "source_location": "L190", "weight": 1.0, "context": "parameter_type"}, {"source": "private_tmp_mer_game_worldchunkfactory_worldchunkfactory_reefclusterzposition", "target": "seededgenerator", "relation": "references", "confidence": "EXTRACTED", "source_file": "Game/WorldChunkFactory.swift", "source_location": "L190", "weight": 1.0, "context": "parameter_type"}, {"source": "private_tmp_mer_game_worldchunkfactory_worldchunkfactory_reefclusterzposition", "target": "cgfloat", "relation": "references", "confidence": "EXTRACTED", "source_file": "Game/WorldChunkFactory.swift", "source_location": "L190", "weight": 1.0, "context": "return_type"}, {"source": "private_tmp_mer_game_worldchunkfactory_worldchunkfactory", "target": "private_tmp_mer_game_worldchunkfactory_worldchunkfactory_addambientemitters", "relation": "method", "confidence": "EXTRACTED", "source_file": "Game/WorldChunkFactory.swift", "source_location": "L197", "weight": 1.0}, {"source": "private_tmp_mer_game_worldchunkfactory_worldchunkfactory_addambientemitters", "target": "sknode", "relation": "references", "confidence": "EXTRACTED", "source_file": "Game/WorldChunkFactory.swift", "source_location": "L197", "weight": 1.0, "context": "parameter_type"}, {"source": "private_tmp_mer_game_worldchunkfactory_worldchunkfactory_addambientemitters", "target": "worldchunkcoord", "relation": "references", "confidence": "EXTRACTED", "source_file": "Game/WorldChunkFactory.swift", "source_location": "L197", "weight": 1.0, "context": "parameter_type"}, {"source": "private_tmp_mer_game_worldchunkfactory_worldchunkfactory_addambientemitters", "target": "depthzone", "relation": "references", "confidence": "EXTRACTED", "source_file": "Game/WorldChunkFactory.swift", "source_location": "L197", "weight": 1.0, "context": "parameter_type"}, {"source": "private_tmp_mer_game_worldchunkfactory_worldchunkfactory_addambientemitters", "target": "aquaticbiome", "relation": "references", "confidence": "EXTRACTED", "source_file": "Game/WorldChunkFactory.swift", "source_location": "L197", "weight": 1.0, "context": "parameter_type"}, {"source": "private_tmp_mer_game_worldchunkfactory_worldchunkfactory", "target": "private_tmp_mer_game_worldchunkfactory_worldchunkfactory_makereefcluster", "relation": "method", "confidence": "EXTRACTED", "source_file": "Game/WorldChunkFactory.swift", "source_location": "L226", "weight": 1.0}, {"source": "private_tmp_mer_game_worldchunkfactory_worldchunkfactory_makereefcluster", "target": "depthzone", "relation": "references", "confidence": "EXTRACTED", "source_file": "Game/WorldChunkFactory.swift", "source_location": "L226", "weight": 1.0, "context": "parameter_type"}, {"source": "private_tmp_mer_game_worldchunkfactory_worldchunkfactory_makereefcluster", "target": "aquaticbiome", "relation": "references", "confidence": "EXTRACTED", "source_file": "Game/WorldChunkFactory.swift", "source_location": "L226", "weight": 1.0, "context": "parameter_type"}, {"source": "private_tmp_mer_game_worldchunkfactory_worldchunkfactory_makereefcluster", "target": "ecosystembiomeprofile", "relation": "references", "confidence": "EXTRACTED", "source_file": "Game/WorldChunkFactory.swift", "source_location": "L226", "weight": 1.0, "context": "parameter_type"}, {"source": "private_tmp_mer_game_worldchunkfactory_worldchunkfactory_makereefcluster", "target": "cgfloat", "relation": "references", "confidence": "EXTRACTED", "source_file": "Game/WorldChunkFactory.swift", "source_location": "L226", "weight": 1.0, "context": "parameter_type"}, {"source": "private_tmp_mer_game_worldchunkfactory_worldchunkfactory_makereefcluster", "target": "seededgenerator", "relation": "references", "confidence": "EXTRACTED", "source_file": "Game/WorldChunkFactory.swift", "source_location": "L226", "weight": 1.0, "context": "parameter_type"}, {"source": "private_tmp_mer_game_worldchunkfactory_worldchunkfactory_makereefcluster", "target": "private_tmp_mer_game_worldchunkfactory_reefcluster", "relation": "references", "confidence": "EXTRACTED", "source_file": "Game/WorldChunkFactory.swift", "source_location": "L226", "weight": 1.0, "context": "return_type"}, {"source": "private_tmp_mer_game_worldchunkfactory_worldchunkfactory", "target": "private_tmp_mer_game_worldchunkfactory_worldchunkfactory_makerocksprite", "relation": "method", "confidence": "EXTRACTED", "source_file": "Game/WorldChunkFactory.swift", "source_location": "L316", "weight": 1.0}, {"source": "private_tmp_mer_game_worldchunkfactory_worldchunkfactory_makerocksprite", "target": "depthzone", "relation": "references", "confidence": "EXTRACTED", "source_file": "Game/WorldChunkFactory.swift", "source_location": "L316", "weight": 1.0, "context": "parameter_type"}, {"source": "private_tmp_mer_game_worldchunkfactory_worldchunkfactory_makerocksprite", "target": "aquaticbiome", "relation": "references", "confidence": "EXTRACTED", "source_file": "Game/WorldChunkFactory.swift", "source_location": "L316", "weight": 1.0, "context": "parameter_type"}, {"source": "private_tmp_mer_game_worldchunkfactory_worldchunkfactory_makerocksprite", "target": "cgsize", "relation": "references", "confidence": "EXTRACTED", "source_file": "Game/WorldChunkFactory.swift", "source_location": "L316", "weight": 1.0, "context": "parameter_type"}, {"source": "private_tmp_mer_game_worldchunkfactory_worldchunkfactory_makerocksprite", "target": "seededgenerator", "relation": "references", "confidence": "EXTRACTED", "source_file": "Game/WorldChunkFactory.swift", "source_location": "L316", "weight": 1.0, "context": "parameter_type"}, {"source": "private_tmp_mer_game_worldchunkfactory_worldchunkfactory_makerocksprite", "target": "skspritenode", "relation": "references", "confidence": "EXTRACTED", "source_file": "Game/WorldChunkFactory.swift", "source_location": "L316", "weight": 1.0, "context": "return_type"}, {"source": "private_tmp_mer_game_worldchunkfactory_worldchunkfactory", "target": "private_tmp_mer_game_worldchunkfactory_worldchunkfactory_makereefskirtsprite", "relation": "method", "confidence": "EXTRACTED", "source_file": "Game/WorldChunkFactory.swift", "source_location": "L330", "weight": 1.0}, {"source": "private_tmp_mer_game_worldchunkfactory_worldchunkfactory_makereefskirtsprite", "target": "depthzone", "relation": "references", "confidence": "EXTRACTED", "source_file": "Game/WorldChunkFactory.swift", "source_location": "L330", "weight": 1.0, "context": "parameter_type"}, {"source": "private_tmp_mer_game_worldchunkfactory_worldchunkfactory_makereefskirtsprite", "target": "aquaticbiome", "relation": "references", "confidence": "EXTRACTED", "source_file": "Game/WorldChunkFactory.swift", "source_location": "L330", "weight": 1.0, "context": "parameter_type"}, {"source": "private_tmp_mer_game_worldchunkfactory_worldchunkfactory_makereefskirtsprite", "target": "cgsize", "relation": "references", "confidence": "EXTRACTED", "source_file": "Game/WorldChunkFactory.swift", "source_location": "L330", "weight": 1.0, "context": "parameter_type"}, {"source": "private_tmp_mer_game_worldchunkfactory_worldchunkfactory_makereefskirtsprite", "target": "seededgenerator", "relation": "references", "confidence": "EXTRACTED", "source_file": "Game/WorldChunkFactory.swift", "source_location": "L330", "weight": 1.0, "context": "parameter_type"}, {"source": "private_tmp_mer_game_worldchunkfactory_worldchunkfactory_makereefskirtsprite", "target": "skspritenode", "relation": "references", "confidence": "EXTRACTED", "source_file": "Game/WorldChunkFactory.swift", "source_location": "L330", "weight": 1.0, "context": "return_type"}, {"source": "private_tmp_mer_game_worldchunkfactory_worldchunkfactory", "target": "private_tmp_mer_game_worldchunkfactory_worldchunkfactory_makekelpsprite", "relation": "method", "confidence": "EXTRACTED", "source_file": "Game/WorldChunkFactory.swift", "source_location": "L347", "weight": 1.0}, {"source": "private_tmp_mer_game_worldchunkfactory_worldchunkfactory_makekelpsprite", "target": "depthzone", "relation": "references", "confidence": "EXTRACTED", "source_file": "Game/WorldChunkFactory.swift", "source_location": "L347", "weight": 1.0, "context": "parameter_type"}, {"source": "private_tmp_mer_game_worldchunkfactory_worldchunkfactory_makekelpsprite", "target": "cgsize", "relation": "references", "confidence": "EXTRACTED", "source_file": "Game/WorldChunkFactory.swift", "source_location": "L347", "weight": 1.0, "context": "parameter_type"}, {"source": "private_tmp_mer_game_worldchunkfactory_worldchunkfactory_makekelpsprite", "target": "worldstampkind", "relation": "references", "confidence": "EXTRACTED", "source_file": "Game/WorldChunkFactory.swift", "source_location": "L347", "weight": 1.0, "context": "parameter_type"}, {"source": "private_tmp_mer_game_worldchunkfactory_worldchunkfactory_makekelpsprite", "target": "seededgenerator", "relation": "references", "confidence": "EXTRACTED", "source_file": "Game/WorldChunkFactory.swift", "source_location": "L347", "weight": 1.0, "context": "parameter_type"}, {"source": "private_tmp_mer_game_worldchunkfactory_worldchunkfactory_makekelpsprite", "target": "skspritenode", "relation": "references", "confidence": "EXTRACTED", "source_file": "Game/WorldChunkFactory.swift", "source_location": "L347", "weight": 1.0, "context": "return_type"}, {"source": "private_tmp_mer_game_worldchunkfactory_worldchunkfactory", "target": "private_tmp_mer_game_worldchunkfactory_worldchunkfactory_makedetailsprite", "relation": "method", "confidence": "EXTRACTED", "source_file": "Game/WorldChunkFactory.swift", "source_location": "L389", "weight": 1.0}, {"source": "private_tmp_mer_game_worldchunkfactory_worldchunkfactory_makedetailsprite", "target": "depthzone", "relation": "references", "confidence": "EXTRACTED", "source_file": "Game/WorldChunkFactory.swift", "source_location": "L389", "weight": 1.0, "context": "parameter_type"}, {"source": "private_tmp_mer_game_worldchunkfactory_worldchunkfactory_makedetailsprite", "target": "aquaticbiome", "relation": "references", "confidence": "EXTRACTED", "source_file": "Game/WorldChunkFactory.swift", "source_location": "L389", "weight": 1.0, "context": "parameter_type"}, {"source": "private_tmp_mer_game_worldchunkfactory_worldchunkfactory_makedetailsprite", "target": "worldstampkind", "relation": "references", "confidence": "EXTRACTED", "source_file": "Game/WorldChunkFactory.swift", "source_location": "L389", "weight": 1.0, "context": "parameter_type"}, {"source": "private_tmp_mer_game_worldchunkfactory_worldchunkfactory_makedetailsprite", "target": "cgsize", "relation": "references", "confidence": "EXTRACTED", "source_file": "Game/WorldChunkFactory.swift", "source_location": "L389", "weight": 1.0, "context": "parameter_type"}, {"source": "private_tmp_mer_game_worldchunkfactory_worldchunkfactory_makedetailsprite", "target": "seededgenerator", "relation": "references", "confidence": "EXTRACTED", "source_file": "Game/WorldChunkFactory.swift", "source_location": "L389", "weight": 1.0, "context": "parameter_type"}, {"source": "private_tmp_mer_game_worldchunkfactory_worldchunkfactory_makedetailsprite", "target": "skspritenode", "relation": "references", "confidence": "EXTRACTED", "source_file": "Game/WorldChunkFactory.swift", "source_location": "L389", "weight": 1.0, "context": "return_type"}, {"source": "private_tmp_mer_game_worldchunkfactory_worldchunkfactory", "target": "private_tmp_mer_game_worldchunkfactory_worldchunkfactory_makeplantsprite", "relation": "method", "confidence": "EXTRACTED", "source_file": "Game/WorldChunkFactory.swift", "source_location": "L411", "weight": 1.0}, {"source": "private_tmp_mer_game_worldchunkfactory_worldchunkfactory_makeplantsprite", "target": "ecosystemvegetationrule", "relation": "references", "confidence": "EXTRACTED", "source_file": "Game/WorldChunkFactory.swift", "source_location": "L411", "weight": 1.0, "context": "parameter_type"}, {"source": "private_tmp_mer_game_worldchunkfactory_worldchunkfactory_makeplantsprite", "target": "depthzone", "relation": "references", "confidence": "EXTRACTED", "source_file": "Game/WorldChunkFactory.swift", "source_location": "L411", "weight": 1.0, "context": "parameter_type"}, {"source": "private_tmp_mer_game_worldchunkfactory_worldchunkfactory_makeplantsprite", "target": "aquaticbiome", "relation": "references", "confidence": "EXTRACTED", "source_file": "Game/WorldChunkFactory.swift", "source_location": "L411", "weight": 1.0, "context": "parameter_type"}, {"source": "private_tmp_mer_game_worldchunkfactory_worldchunkfactory_makeplantsprite", "target": "cgsize", "relation": "references", "confidence": "EXTRACTED", "source_file": "Game/WorldChunkFactory.swift", "source_location": "L411", "weight": 1.0, "context": "parameter_type"}, {"source": "private_tmp_mer_game_worldchunkfactory_worldchunkfactory_makeplantsprite", "target": "seededgenerator", "relation": "references", "confidence": "EXTRACTED", "source_file": "Game/WorldChunkFactory.swift", "source_location": "L411", "weight": 1.0, "context": "parameter_type"}, {"source": "private_tmp_mer_game_worldchunkfactory_worldchunkfactory_makeplantsprite", "target": "skspritenode", "relation": "references", "confidence": "EXTRACTED", "source_file": "Game/WorldChunkFactory.swift", "source_location": "L411", "weight": 1.0, "context": "return_type"}, {"source": "private_tmp_mer_game_worldchunkfactory_worldchunkfactory", "target": "private_tmp_mer_game_worldchunkfactory_worldchunkfactory_makedetailsprite", "relation": "method", "confidence": "EXTRACTED", "source_file": "Game/WorldChunkFactory.swift", "source_location": "L427", "weight": 1.0}, {"source": "private_tmp_mer_game_worldchunkfactory_worldchunkfactory_makedetailsprite", "target": "ecosystemvegetationrule", "relation": "references", "confidence": "EXTRACTED", "source_file": "Game/WorldChunkFactory.swift", "source_location": "L427", "weight": 1.0, "context": "parameter_type"}, {"source": "private_tmp_mer_game_worldchunkfactory_worldchunkfactory_makedetailsprite", "target": "depthzone", "relation": "references", "confidence": "EXTRACTED", "source_file": "Game/WorldChunkFactory.swift", "source_location": "L427", "weight": 1.0, "context": "parameter_type"}, {"source": "private_tmp_mer_game_worldchunkfactory_worldchunkfactory_makedetailsprite", "target": "aquaticbiome", "relation": "references", "confidence": "EXTRACTED", "source_file": "Game/WorldChunkFactory.swift", "source_location": "L427", "weight": 1.0, "context": "parameter_type"}, {"source": "private_tmp_mer_game_worldchunkfactory_worldchunkfactory_makedetailsprite", "target": "cgsize", "relation": "references", "confidence": "EXTRACTED", "source_file": "Game/WorldChunkFactory.swift", "source_location": "L427", "weight": 1.0, "context": "parameter_type"}, {"source": "private_tmp_mer_game_worldchunkfactory_worldchunkfactory_makedetailsprite", "target": "seededgenerator", "relation": "references", "confidence": "EXTRACTED", "source_file": "Game/WorldChunkFactory.swift", "source_location": "L427", "weight": 1.0, "context": "parameter_type"}, {"source": "private_tmp_mer_game_worldchunkfactory_worldchunkfactory_makedetailsprite", "target": "skspritenode", "relation": "references", "confidence": "EXTRACTED", "source_file": "Game/WorldChunkFactory.swift", "source_location": "L427", "weight": 1.0, "context": "return_type"}, {"source": "private_tmp_mer_game_worldchunkfactory_worldchunkfactory", "target": "private_tmp_mer_game_worldchunkfactory_worldchunkfactory_fitplantsprite", "relation": "method", "confidence": "EXTRACTED", "source_file": "Game/WorldChunkFactory.swift", "source_location": "L439", "weight": 1.0}, {"source": "private_tmp_mer_game_worldchunkfactory_worldchunkfactory_fitplantsprite", "target": "skspritenode", "relation": "references", "confidence": "EXTRACTED", "source_file": "Game/WorldChunkFactory.swift", "source_location": "L439", "weight": 1.0, "context": "parameter_type"}, {"source": "private_tmp_mer_game_worldchunkfactory_worldchunkfactory_fitplantsprite", "target": "worldstampkind", "relation": "references", "confidence": "EXTRACTED", "source_file": "Game/WorldChunkFactory.swift", "source_location": "L439", "weight": 1.0, "context": "parameter_type"}, {"source": "private_tmp_mer_game_worldchunkfactory_worldchunkfactory_fitplantsprite", "target": "cgsize", "relation": "references", "confidence": "EXTRACTED", "source_file": "Game/WorldChunkFactory.swift", "source_location": "L439", "weight": 1.0, "context": "parameter_type"}, {"source": "private_tmp_mer_game_worldchunkfactory_worldchunkfactory", "target": "private_tmp_mer_game_worldchunkfactory_worldchunkfactory_plantingx", "relation": "method", "confidence": "EXTRACTED", "source_file": "Game/WorldChunkFactory.swift", "source_location": "L473", "weight": 1.0}, {"source": "private_tmp_mer_game_worldchunkfactory_worldchunkfactory_plantingx", "target": "skspritenode", "relation": "references", "confidence": "EXTRACTED", "source_file": "Game/WorldChunkFactory.swift", "source_location": "L473", "weight": 1.0, "context": "parameter_type"}, {"source": "private_tmp_mer_game_worldchunkfactory_worldchunkfactory_plantingx", "target": "cgsize", "relation": "references", "confidence": "EXTRACTED", "source_file": "Game/WorldChunkFactory.swift", "source_location": "L473", "weight": 1.0, "context": "parameter_type"}, {"source": "private_tmp_mer_game_worldchunkfactory_worldchunkfactory_plantingx", "target": "seededgenerator", "relation": "references", "confidence": "EXTRACTED", "source_file": "Game/WorldChunkFactory.swift", "source_location": "L473", "weight": 1.0, "context": "parameter_type"}, {"source": "private_tmp_mer_game_worldchunkfactory_worldchunkfactory_plantingx", "target": "cgfloat", "relation": "references", "confidence": "EXTRACTED", "source_file": "Game/WorldChunkFactory.swift", "source_location": "L473", "weight": 1.0, "context": "return_type"}, {"source": "private_tmp_mer_game_worldchunkfactory_worldchunkfactory", "target": "private_tmp_mer_game_worldchunkfactory_worldchunkfactory_plantingsurfacey", "relation": "method", "confidence": "EXTRACTED", "source_file": "Game/WorldChunkFactory.swift", "source_location": "L485", "weight": 1.0}, {"source": "private_tmp_mer_game_worldchunkfactory_worldchunkfactory_plantingsurfacey", "target": "cgfloat", "relation": "references", "confidence": "EXTRACTED", "source_file": "Game/WorldChunkFactory.swift", "source_location": "L485", "weight": 1.0, "context": "parameter_type"}, {"source": "private_tmp_mer_game_worldchunkfactory_worldchunkfactory_plantingsurfacey", "target": "cgsize", "relation": "references", "confidence": "EXTRACTED", "source_file": "Game/WorldChunkFactory.swift", "source_location": "L485", "weight": 1.0, "context": "parameter_type"}, {"source": "private_tmp_mer_game_worldchunkfactory_worldchunkfactory_plantingsurfacey", "target": "seededgenerator", "relation": "references", "confidence": "EXTRACTED", "source_file": "Game/WorldChunkFactory.swift", "source_location": "L485", "weight": 1.0, "context": "parameter_type"}, {"source": "private_tmp_mer_game_worldchunkfactory_worldchunkfactory_plantingsurfacey", "target": "cgfloat", "relation": "references", "confidence": "EXTRACTED", "source_file": "Game/WorldChunkFactory.swift", "source_location": "L485", "weight": 1.0, "context": "return_type"}, {"source": "private_tmp_mer_game_worldchunkfactory_worldchunkfactory", "target": "private_tmp_mer_game_worldchunkfactory_worldchunkfactory_rootsink", "relation": "method", "confidence": "EXTRACTED", "source_file": "Game/WorldChunkFactory.swift", "source_location": "L497", "weight": 1.0}, {"source": "private_tmp_mer_game_worldchunkfactory_worldchunkfactory_rootsink", "target": "skspritenode", "relation": "references", "confidence": "EXTRACTED", "source_file": "Game/WorldChunkFactory.swift", "source_location": "L497", "weight": 1.0, "context": "parameter_type"}, {"source": "private_tmp_mer_game_worldchunkfactory_worldchunkfactory_rootsink", "target": "seededgenerator", "relation": "references", "confidence": "EXTRACTED", "source_file": "Game/WorldChunkFactory.swift", "source_location": "L497", "weight": 1.0, "context": "parameter_type"}, {"source": "private_tmp_mer_game_worldchunkfactory_worldchunkfactory_rootsink", "target": "cgfloat", "relation": "references", "confidence": "EXTRACTED", "source_file": "Game/WorldChunkFactory.swift", "source_location": "L497", "weight": 1.0, "context": "return_type"}, {"source": "private_tmp_mer_game_worldchunkfactory_worldchunkfactory", "target": "private_tmp_mer_game_worldchunkfactory_worldchunkfactory_rootanchory", "relation": "method", "confidence": "EXTRACTED", "source_file": "Game/WorldChunkFactory.swift", "source_location": "L502", "weight": 1.0}, {"source": "private_tmp_mer_game_worldchunkfactory_worldchunkfactory_rootanchory", "target": "worldstampkind", "relation": "references", "confidence": "EXTRACTED", "source_file": "Game/WorldChunkFactory.swift", "source_location": "L502", "weight": 1.0, "context": "parameter_type"}, {"source": "private_tmp_mer_game_worldchunkfactory_worldchunkfactory_rootanchory", "target": "cgfloat", "relation": "references", "confidence": "EXTRACTED", "source_file": "Game/WorldChunkFactory.swift", "source_location": "L502", "weight": 1.0, "context": "return_type"}, {"source": "private_tmp_mer_game_worldchunkfactory_worldchunkfactory", "target": "private_tmp_mer_game_worldchunkfactory_worldchunkfactory_detailsize", "relation": "method", "confidence": "EXTRACTED", "source_file": "Game/WorldChunkFactory.swift", "source_location": "L525", "weight": 1.0}, {"source": "private_tmp_mer_game_worldchunkfactory_worldchunkfactory_detailsize", "target": "worldstampkind", "relation": "references", "confidence": "EXTRACTED", "source_file": "Game/WorldChunkFactory.swift", "source_location": "L525", "weight": 1.0, "context": "parameter_type"}, {"source": "private_tmp_mer_game_worldchunkfactory_worldchunkfactory_detailsize", "target": "depthzone", "relation": "references", "confidence": "EXTRACTED", "source_file": "Game/WorldChunkFactory.swift", "source_location": "L525", "weight": 1.0, "context": "parameter_type"}, {"source": "private_tmp_mer_game_worldchunkfactory_worldchunkfactory_detailsize", "target": "aquaticbiome", "relation": "references", "confidence": "EXTRACTED", "source_file": "Game/WorldChunkFactory.swift", "source_location": "L525", "weight": 1.0, "context": "parameter_type"}, {"source": "private_tmp_mer_game_worldchunkfactory_worldchunkfactory_detailsize", "target": "seededgenerator", "relation": "references", "confidence": "EXTRACTED", "source_file": "Game/WorldChunkFactory.swift", "source_location": "L525", "weight": 1.0, "context": "parameter_type"}, {"source": "private_tmp_mer_game_worldchunkfactory_worldchunkfactory_detailsize", "target": "cgsize", "relation": "references", "confidence": "EXTRACTED", "source_file": "Game/WorldChunkFactory.swift", "source_location": "L525", "weight": 1.0, "context": "return_type"}, {"source": "private_tmp_mer_game_worldchunkfactory_worldchunkfactory", "target": "private_tmp_mer_game_worldchunkfactory_worldchunkfactory_reefdensity", "relation": "method", "confidence": "EXTRACTED", "source_file": "Game/WorldChunkFactory.swift", "source_location": "L558", "weight": 1.0}, {"source": "private_tmp_mer_game_worldchunkfactory_worldchunkfactory_reefdensity", "target": "depthzone", "relation": "references", "confidence": "EXTRACTED", "source_file": "Game/WorldChunkFactory.swift", "source_location": "L558", "weight": 1.0, "context": "parameter_type"}, {"source": "private_tmp_mer_game_worldchunkfactory_worldchunkfactory_reefdensity", "target": "aquaticbiome", "relation": "references", "confidence": "EXTRACTED", "source_file": "Game/WorldChunkFactory.swift", "source_location": "L558", "weight": 1.0, "context": "parameter_type"}, {"source": "private_tmp_mer_game_worldchunkfactory_worldchunkfactory_reefdensity", "target": "ecosystembiomeprofile", "relation": "references", "confidence": "EXTRACTED", "source_file": "Game/WorldChunkFactory.swift", "source_location": "L558", "weight": 1.0, "context": "parameter_type"}, {"source": "private_tmp_mer_game_worldchunkfactory_worldchunkfactory_reefdensity", "target": "seededgenerator", "relation": "references", "confidence": "EXTRACTED", "source_file": "Game/WorldChunkFactory.swift", "source_location": "L558", "weight": 1.0, "context": "parameter_type"}, {"source": "private_tmp_mer_game_worldchunkfactory_worldchunkfactory_reefdensity", "target": "cgfloat", "relation": "references", "confidence": "EXTRACTED", "source_file": "Game/WorldChunkFactory.swift", "source_location": "L558", "weight": 1.0, "context": "return_type"}, {"source": "private_tmp_mer_game_worldchunkfactory_worldchunkfactory", "target": "private_tmp_mer_game_worldchunkfactory_worldchunkfactory_randompoint", "relation": "method", "confidence": "EXTRACTED", "source_file": "Game/WorldChunkFactory.swift", "source_location": "L597", "weight": 1.0}, {"source": "private_tmp_mer_game_worldchunkfactory_worldchunkfactory_randompoint", "target": "cgrect", "relation": "references", "confidence": "EXTRACTED", "source_file": "Game/WorldChunkFactory.swift", "source_location": "L597", "weight": 1.0, "context": "parameter_type"}, {"source": "private_tmp_mer_game_worldchunkfactory_worldchunkfactory_randompoint", "target": "cgfloat", "relation": "references", "confidence": "EXTRACTED", "source_file": "Game/WorldChunkFactory.swift", "source_location": "L597", "weight": 1.0, "context": "parameter_type"}, {"source": "private_tmp_mer_game_worldchunkfactory_worldchunkfactory_randompoint", "target": "seededgenerator", "relation": "references", "confidence": "EXTRACTED", "source_file": "Game/WorldChunkFactory.swift", "source_location": "L597", "weight": 1.0, "context": "parameter_type"}, {"source": "private_tmp_mer_game_worldchunkfactory_worldchunkfactory_randompoint", "target": "cgpoint", "relation": "references", "confidence": "EXTRACTED", "source_file": "Game/WorldChunkFactory.swift", "source_location": "L597", "weight": 1.0, "context": "return_type"}, {"source": "private_tmp_mer_game_worldchunkfactory_worldchunkfactory_makechunk", "target": "private_tmp_mer_game_worldchunkfactory_worldchunkfactory_makeproceduralchunk", "relation": "calls", "context": "call", "confidence": "EXTRACTED", "source_file": "Game/WorldChunkFactory.swift", "source_location": "L26", "weight": 1.0}, {"source": "private_tmp_mer_game_worldchunkfactory_worldchunkfactory_makeproceduralchunk", "target": "sknode", "relation": "calls", "context": "call", "confidence": "EXTRACTED", "source_file": "Game/WorldChunkFactory.swift", "source_location": "L34", "weight": 1.0}, {"source": "private_tmp_mer_game_worldchunkfactory_worldchunkfactory_makeproceduralchunk", "target": "cgfloat", "relation": "calls", "context": "call", "confidence": "EXTRACTED", "source_file": "Game/WorldChunkFactory.swift", "source_location": "L36", "weight": 1.0}, {"source": "private_tmp_mer_game_worldchunkfactory_worldchunkfactory_makeproceduralchunk", "target": "private_tmp_mer_game_worldchunkfactory_worldchunkfactory_addmacroforms", "relation": "calls", "context": "call", "confidence": "EXTRACTED", "source_file": "Game/WorldChunkFactory.swift", "source_location": "L40", "weight": 1.0}, {"source": "private_tmp_mer_game_worldchunkfactory_worldchunkfactory_makeproceduralchunk", "target": "private_tmp_mer_game_worldchunkfactory_worldchunkfactory_addcurrents", "relation": "calls", "context": "call", "confidence": "EXTRACTED", "source_file": "Game/WorldChunkFactory.swift", "source_location": "L41", "weight": 1.0}, {"source": "private_tmp_mer_game_worldchunkfactory_worldchunkfactory_makeproceduralchunk", "target": "private_tmp_mer_game_worldchunkfactory_worldchunkfactory_addreefs", "relation": "calls", "context": "call", "confidence": "EXTRACTED", "source_file": "Game/WorldChunkFactory.swift", "source_location": "L42", "weight": 1.0}, {"source": "private_tmp_mer_game_worldchunkfactory_worldchunkfactory_makeproceduralchunk", "target": "private_tmp_mer_game_worldchunkfactory_worldchunkfactory_addambientemitters", "relation": "calls", "context": "call", "confidence": "EXTRACTED", "source_file": "Game/WorldChunkFactory.swift", "source_location": "L44", "weight": 1.0}, {"source": "private_tmp_mer_game_worldchunkfactory_worldchunkfactory_addmacroforms", "target": "seededgenerator", "relation": "calls", "context": "call", "confidence": "EXTRACTED", "source_file": "Game/WorldChunkFactory.swift", "source_location": "L53", "weight": 1.0}, {"source": "private_tmp_mer_game_worldchunkfactory_worldchunkfactory_addmacroforms", "target": "skspritenode", "relation": "calls", "context": "call", "confidence": "EXTRACTED", "source_file": "Game/WorldChunkFactory.swift", "source_location": "L71", "weight": 1.0}, {"source": "private_tmp_mer_game_worldchunkfactory_worldchunkfactory_addmacroforms", "target": "cgsize", "relation": "calls", "context": "call", "confidence": "EXTRACTED", "source_file": "Game/WorldChunkFactory.swift", "source_location": "L72", "weight": 1.0}, {"source": "private_tmp_mer_game_worldchunkfactory_worldchunkfactory_addmacroforms", "target": "private_tmp_mer_game_worldchunkfactory_worldchunkfactory_randompoint", "relation": "calls", "context": "call", "confidence": "EXTRACTED", "source_file": "Game/WorldChunkFactory.swift", "source_location": "L74", "weight": 1.0}, {"source": "private_tmp_mer_game_worldchunkfactory_worldchunkfactory_addcurrents", "target": "seededgenerator", "relation": "calls", "context": "call", "confidence": "EXTRACTED", "source_file": "Game/WorldChunkFactory.swift", "source_location": "L88", "weight": 1.0}, {"source": "private_tmp_mer_game_worldchunkfactory_worldchunkfactory_addcurrents", "target": "skspritenode", "relation": "calls", "context": "call", "confidence": "EXTRACTED", "source_file": "Game/WorldChunkFactory.swift", "source_location": "L97", "weight": 1.0}, {"source": "private_tmp_mer_game_worldchunkfactory_worldchunkfactory_addcurrents", "target": "cgsize", "relation": "calls", "context": "call", "confidence": "EXTRACTED", "source_file": "Game/WorldChunkFactory.swift", "source_location": "L98", "weight": 1.0}, {"source": "private_tmp_mer_game_worldchunkfactory_worldchunkfactory_addcurrents", "target": "private_tmp_mer_game_worldchunkfactory_worldchunkfactory_randompoint", "relation": "calls", "context": "call", "confidence": "EXTRACTED", "source_file": "Game/WorldChunkFactory.swift", "source_location": "L100", "weight": 1.0}, {"source": "private_tmp_mer_game_worldchunkfactory_worldchunkfactory_addreefs", "target": "seededgenerator", "relation": "calls", "context": "call", "confidence": "EXTRACTED", "source_file": "Game/WorldChunkFactory.swift", "source_location": "L114", "weight": 1.0}, {"source": "private_tmp_mer_game_worldchunkfactory_worldchunkfactory_addreefs", "target": "private_tmp_mer_game_worldchunkfactory_worldchunkfactory_reefdensity", "relation": "calls", "context": "call", "confidence": "EXTRACTED", "source_file": "Game/WorldChunkFactory.swift", "source_location": "L115", "weight": 1.0}, {"source": "private_tmp_mer_game_worldchunkfactory_worldchunkfactory_addreefs", "target": "private_tmp_mer_game_worldchunkfactory_worldchunkfactory_makereefcluster", "relation": "calls", "context": "call", "confidence": "EXTRACTED", "source_file": "Game/WorldChunkFactory.swift", "source_location": "L126", "weight": 1.0}, {"source": "private_tmp_mer_game_worldchunkfactory_worldchunkfactory_addreefs", "target": "private_tmp_mer_game_worldchunkfactory_worldchunkfactory_reefclusterposition", "relation": "calls", "context": "call", "confidence": "EXTRACTED", "source_file": "Game/WorldChunkFactory.swift", "source_location": "L132", "weight": 1.0}, {"source": "private_tmp_mer_game_worldchunkfactory_worldchunkfactory_addreefs", "target": "private_tmp_mer_game_worldchunkfactory_worldchunkfactory_reefclusterzposition", "relation": "calls", "context": "call", "confidence": "EXTRACTED", "source_file": "Game/WorldChunkFactory.swift", "source_location": "L141", "weight": 1.0}, {"source": "private_tmp_mer_game_worldchunkfactory_worldchunkfactory_addreefs", "target": "private_tmp_mer_game_worldchunkfactory_placedreefcluster", "relation": "calls", "context": "call", "confidence": "EXTRACTED", "source_file": "Game/WorldChunkFactory.swift", "source_location": "L144", "weight": 1.0}, {"source": "private_tmp_mer_game_worldchunkfactory_worldchunkfactory_reefclusterposition", "target": "cgpoint", "relation": "calls", "context": "call", "confidence": "EXTRACTED", "source_file": "Game/WorldChunkFactory.swift", "source_location": "L162", "weight": 1.0}, {"source": "private_tmp_mer_game_worldchunkfactory_worldchunkfactory_hasverticalconflict", "target": "cgfloat", "relation": "calls", "context": "call", "confidence": "EXTRACTED", "source_file": "Game/WorldChunkFactory.swift", "source_location": "L182", "weight": 1.0}, {"source": "private_tmp_mer_game_worldchunkfactory_worldchunkfactory_addambientemitters", "target": "seededgenerator", "relation": "calls", "context": "call", "confidence": "EXTRACTED", "source_file": "Game/WorldChunkFactory.swift", "source_location": "L202", "weight": 1.0}, {"source": "private_tmp_mer_game_worldchunkfactory_worldchunkfactory_makereefcluster", "target": "sknode", "relation": "calls", "context": "call", "confidence": "EXTRACTED", "source_file": "Game/WorldChunkFactory.swift", "source_location": "L231", "weight": 1.0}, {"source": "private_tmp_mer_game_worldchunkfactory_worldchunkfactory_makereefcluster", "target": "cgsize", "relation": "calls", "context": "call", "confidence": "EXTRACTED", "source_file": "Game/WorldChunkFactory.swift", "source_location": "L232", "weight": 1.0}, {"source": "private_tmp_mer_game_worldchunkfactory_worldchunkfactory_makereefcluster", "target": "private_tmp_mer_game_worldchunkfactory_worldchunkfactory_makerocksprite", "relation": "calls", "context": "call", "confidence": "EXTRACTED", "source_file": "Game/WorldChunkFactory.swift", "source_location": "L236", "weight": 1.0}, {"source": "private_tmp_mer_game_worldchunkfactory_worldchunkfactory_makereefcluster", "target": "private_tmp_mer_game_worldchunkfactory_worldchunkfactory_makereefskirtsprite", "relation": "calls", "context": "call", "confidence": "EXTRACTED", "source_file": "Game/WorldChunkFactory.swift", "source_location": "L242", "weight": 1.0}, {"source": "private_tmp_mer_game_worldchunkfactory_worldchunkfactory_makereefcluster", "target": "cgpoint", "relation": "calls", "context": "call", "confidence": "EXTRACTED", "source_file": "Game/WorldChunkFactory.swift", "source_location": "L243", "weight": 1.0}, {"source": "private_tmp_mer_game_worldchunkfactory_worldchunkfactory_makereefcluster", "target": "private_tmp_mer_game_worldchunkfactory_worldchunkfactory_makeplantsprite", "relation": "calls", "context": "call", "confidence": "EXTRACTED", "source_file": "Game/WorldChunkFactory.swift", "source_location": "L281", "weight": 1.0}, {"source": "private_tmp_mer_game_worldchunkfactory_worldchunkfactory_makereefcluster", "target": "private_tmp_mer_game_worldchunkfactory_worldchunkfactory_plantingx", "relation": "calls", "context": "call", "confidence": "EXTRACTED", "source_file": "Game/WorldChunkFactory.swift", "source_location": "L286", "weight": 1.0}, {"source": "private_tmp_mer_game_worldchunkfactory_worldchunkfactory_makereefcluster", "target": "private_tmp_mer_game_worldchunkfactory_worldchunkfactory_plantingsurfacey", "relation": "calls", "context": "call", "confidence": "EXTRACTED", "source_file": "Game/WorldChunkFactory.swift", "source_location": "L287", "weight": 1.0}, {"source": "private_tmp_mer_game_worldchunkfactory_worldchunkfactory_makereefcluster", "target": "private_tmp_mer_game_worldchunkfactory_worldchunkfactory_makedetailsprite", "relation": "calls", "context": "call", "confidence": "EXTRACTED", "source_file": "Game/WorldChunkFactory.swift", "source_location": "L298", "weight": 1.0}, {"source": "private_tmp_mer_game_worldchunkfactory_worldchunkfactory_makereefcluster", "target": "private_tmp_mer_game_worldchunkfactory_reefcluster", "relation": "calls", "context": "call", "confidence": "EXTRACTED", "source_file": "Game/WorldChunkFactory.swift", "source_location": "L311", "weight": 1.0}, {"source": "private_tmp_mer_game_worldchunkfactory_worldchunkfactory_makerocksprite", "target": "skspritenode", "relation": "calls", "context": "call", "confidence": "EXTRACTED", "source_file": "Game/WorldChunkFactory.swift", "source_location": "L324", "weight": 1.0}, {"source": "private_tmp_mer_game_worldchunkfactory_worldchunkfactory_makerocksprite", "target": "cgpoint", "relation": "calls", "context": "call", "confidence": "EXTRACTED", "source_file": "Game/WorldChunkFactory.swift", "source_location": "L326", "weight": 1.0}, {"source": "private_tmp_mer_game_worldchunkfactory_worldchunkfactory_makereefskirtsprite", "target": "skspritenode", "relation": "calls", "context": "call", "confidence": "EXTRACTED", "source_file": "Game/WorldChunkFactory.swift", "source_location": "L338", "weight": 1.0}, {"source": "private_tmp_mer_game_worldchunkfactory_worldchunkfactory_makereefskirtsprite", "target": "cgsize", "relation": "calls", "context": "call", "confidence": "EXTRACTED", "source_file": "Game/WorldChunkFactory.swift", "source_location": "L339", "weight": 1.0}, {"source": "private_tmp_mer_game_worldchunkfactory_worldchunkfactory_makereefskirtsprite", "target": "cgpoint", "relation": "calls", "context": "call", "confidence": "EXTRACTED", "source_file": "Game/WorldChunkFactory.swift", "source_location": "L341", "weight": 1.0}, {"source": "private_tmp_mer_game_worldchunkfactory_worldchunkfactory_makekelpsprite", "target": "skspritenode", "relation": "calls", "context": "call", "confidence": "EXTRACTED", "source_file": "Game/WorldChunkFactory.swift", "source_location": "L369", "weight": 1.0}, {"source": "private_tmp_mer_game_worldchunkfactory_worldchunkfactory_makekelpsprite", "target": "cgsize", "relation": "calls", "context": "call", "confidence": "EXTRACTED", "source_file": "Game/WorldChunkFactory.swift", "source_location": "L370", "weight": 1.0}, {"source": "private_tmp_mer_game_worldchunkfactory_worldchunkfactory_makekelpsprite", "target": "cgpoint", "relation": "calls", "context": "call", "confidence": "EXTRACTED", "source_file": "Game/WorldChunkFactory.swift", "source_location": "L372", "weight": 1.0}, {"source": "private_tmp_mer_game_worldchunkfactory_worldchunkfactory_makekelpsprite", "target": "private_tmp_mer_game_worldchunkfactory_worldchunkfactory_rootanchory", "relation": "calls", "context": "call", "confidence": "EXTRACTED", "source_file": "Game/WorldChunkFactory.swift", "source_location": "L372", "weight": 1.0}, {"source": "private_tmp_mer_game_worldchunkfactory_worldchunkfactory_makekelpsprite", "target": "private_tmp_mer_game_worldchunkfactory_worldchunkfactory_fitplantsprite", "relation": "calls", "context": "call", "confidence": "EXTRACTED", "source_file": "Game/WorldChunkFactory.swift", "source_location": "L373", "weight": 1.0}, {"source": "private_tmp_mer_game_worldchunkfactory_worldchunkfactory_makedetailsprite", "target": "skspritenode", "relation": "calls", "context": "call", "confidence": "EXTRACTED", "source_file": "Game/WorldChunkFactory.swift", "source_location": "L398", "weight": 1.0}, {"source": "private_tmp_mer_game_worldchunkfactory_worldchunkfactory_makedetailsprite", "target": "private_tmp_mer_game_worldchunkfactory_worldchunkfactory_detailsize", "relation": "calls", "context": "call", "confidence": "EXTRACTED", "source_file": "Game/WorldChunkFactory.swift", "source_location": "L399", "weight": 1.0}, {"source": "private_tmp_mer_game_worldchunkfactory_worldchunkfactory_makedetailsprite", "target": "cgpoint", "relation": "calls", "context": "call", "confidence": "EXTRACTED", "source_file": "Game/WorldChunkFactory.swift", "source_location": "L400", "weight": 1.0}, {"source": "private_tmp_mer_game_worldchunkfactory_worldchunkfactory_makedetailsprite", "target": "private_tmp_mer_game_worldchunkfactory_worldchunkfactory_rootanchory", "relation": "calls", "context": "call", "confidence": "EXTRACTED", "source_file": "Game/WorldChunkFactory.swift", "source_location": "L400", "weight": 1.0}, {"source": "private_tmp_mer_game_worldchunkfactory_worldchunkfactory_makedetailsprite", "target": "private_tmp_mer_game_worldchunkfactory_worldchunkfactory_fitplantsprite", "relation": "calls", "context": "call", "confidence": "EXTRACTED", "source_file": "Game/WorldChunkFactory.swift", "source_location": "L401", "weight": 1.0}, {"source": "private_tmp_mer_game_worldchunkfactory_worldchunkfactory_makeplantsprite", "target": "private_tmp_mer_game_worldchunkfactory_worldchunkfactory_makekelpsprite", "relation": "calls", "context": "call", "confidence": "EXTRACTED", "source_file": "Game/WorldChunkFactory.swift", "source_location": "L418", "weight": 1.0}, {"source": "private_tmp_mer_game_worldchunkfactory_worldchunkfactory_makeplantsprite", "target": "private_tmp_mer_game_worldchunkfactory_worldchunkfactory_makedetailsprite", "relation": "calls", "context": "call", "confidence": "EXTRACTED", "source_file": "Game/WorldChunkFactory.swift", "source_location": "L423", "weight": 1.0}, {"source": "private_tmp_mer_game_worldchunkfactory_worldchunkfactory_fitplantsprite", "target": "cgsize", "relation": "calls", "context": "call", "confidence": "EXTRACTED", "source_file": "Game/WorldChunkFactory.swift", "source_location": "L468", "weight": 1.0}, {"source": "private_tmp_mer_game_worldchunkfactory_worldchunkfactory_detailsize", "target": "cgsize", "relation": "calls", "context": "call", "confidence": "EXTRACTED", "source_file": "Game/WorldChunkFactory.swift", "source_location": "L531", "weight": 1.0}, {"source": "private_tmp_mer_game_worldchunkfactory_worldchunkfactory_randompoint", "target": "cgpoint", "relation": "calls", "context": "call", "confidence": "EXTRACTED", "source_file": "Game/WorldChunkFactory.swift", "source_location": "L600", "weight": 1.0}], "raw_calls": [{"caller_nid": "private_tmp_mer_game_worldchunkfactory_worldchunkfactory_makechunk", "callee": "profile", "is_member_call": true, "source_file": "/private/tmp/mer/Game/WorldChunkFactory.swift", "source_location": "L25", "receiver": "EcosystemBiomeCatalog"}, {"caller_nid": "private_tmp_mer_game_worldchunkfactory_worldchunkfactory_makeproceduralchunk", "callee": "zone", "is_member_call": true, "source_file": "/private/tmp/mer/Game/WorldChunkFactory.swift", "source_location": "L38", "receiver": "DepthZone"}, {"caller_nid": "private_tmp_mer_game_worldchunkfactory_worldchunkfactory_makeproceduralchunk", "callee": "subBiome", "is_member_call": true, "source_file": "/private/tmp/mer/Game/WorldChunkFactory.swift", "source_location": "L39", "receiver": "profile"}, {"caller_nid": "private_tmp_mer_game_worldchunkfactory_worldchunkfactory_addmacroforms", "callee": "seedForChunk", "is_member_call": true, "source_file": "/private/tmp/mer/Game/WorldChunkFactory.swift", "source_location": "L53", "receiver": "WorldSeed"}, {"caller_nid": "private_tmp_mer_game_worldchunkfactory_worldchunkfactory_addmacroforms", "callee": "chance", "is_member_call": true, "source_file": "/private/tmp/mer/Game/WorldChunkFactory.swift", "source_location": "L57", "receiver": "rng"}, {"caller_nid": "private_tmp_mer_game_worldchunkfactory_worldchunkfactory_addmacroforms", "callee": "chance", "is_member_call": true, "source_file": "/private/tmp/mer/Game/WorldChunkFactory.swift", "source_location": "L59", "receiver": "rng"}, {"caller_nid": "private_tmp_mer_game_worldchunkfactory_worldchunkfactory_addmacroforms", "callee": "nextInt", "is_member_call": true, "source_file": "/private/tmp/mer/Game/WorldChunkFactory.swift", "source_location": "L61", "receiver": "rng"}, {"caller_nid": "private_tmp_mer_game_worldchunkfactory_worldchunkfactory_addmacroforms", "callee": "chance", "is_member_call": true, "source_file": "/private/tmp/mer/Game/WorldChunkFactory.swift", "source_location": "L63", "receiver": "rng"}, {"caller_nid": "private_tmp_mer_game_worldchunkfactory_worldchunkfactory_addmacroforms", "callee": "texture", "is_member_call": true, "source_file": "/private/tmp/mer/Game/WorldChunkFactory.swift", "source_location": "L67", "receiver": "WorldTextureCache"}, {"caller_nid": "private_tmp_mer_game_worldchunkfactory_worldchunkfactory_addmacroforms", "callee": "nextInt", "is_member_call": true, "source_file": "/private/tmp/mer/Game/WorldChunkFactory.swift", "source_location": "L70", "receiver": "rng"}, {"caller_nid": "private_tmp_mer_game_worldchunkfactory_worldchunkfactory_addmacroforms", "callee": "nextCGFloat", "is_member_call": true, "source_file": "/private/tmp/mer/Game/WorldChunkFactory.swift", "source_location": "L72", "receiver": "rng"}, {"caller_nid": "private_tmp_mer_game_worldchunkfactory_worldchunkfactory_addmacroforms", "callee": "nextCGFloat", "is_member_call": true, "source_file": "/private/tmp/mer/Game/WorldChunkFactory.swift", "source_location": "L73", "receiver": "rng"}, {"caller_nid": "private_tmp_mer_game_worldchunkfactory_worldchunkfactory_addmacroforms", "callee": "macroAlpha", "is_member_call": true, "source_file": "/private/tmp/mer/Game/WorldChunkFactory.swift", "source_location": "L76", "receiver": "WorldVisualPalette"}, {"caller_nid": "private_tmp_mer_game_worldchunkfactory_worldchunkfactory_addmacroforms", "callee": "nextCGFloat", "is_member_call": true, "source_file": "/private/tmp/mer/Game/WorldChunkFactory.swift", "source_location": "L77", "receiver": "rng"}, {"caller_nid": "private_tmp_mer_game_worldchunkfactory_worldchunkfactory_addmacroforms", "callee": "addChild", "is_member_call": true, "source_file": "/private/tmp/mer/Game/WorldChunkFactory.swift", "source_location": "L79", "receiver": "node"}, {"caller_nid": "private_tmp_mer_game_worldchunkfactory_worldchunkfactory_addcurrents", "callee": "seedForChunk", "is_member_call": true, "source_file": "/private/tmp/mer/Game/WorldChunkFactory.swift", "source_location": "L88", "receiver": "WorldSeed"}, {"caller_nid": "private_tmp_mer_game_worldchunkfactory_worldchunkfactory_addcurrents", "callee": "texture", "is_member_call": true, "source_file": "/private/tmp/mer/Game/WorldChunkFactory.swift", "source_location": "L93", "receiver": "WorldTextureCache"}, {"caller_nid": "private_tmp_mer_game_worldchunkfactory_worldchunkfactory_addcurrents", "callee": "nextInt", "is_member_call": true, "source_file": "/private/tmp/mer/Game/WorldChunkFactory.swift", "source_location": "L96", "receiver": "rng"}, {"caller_nid": "private_tmp_mer_game_worldchunkfactory_worldchunkfactory_addcurrents", "callee": "nextCGFloat", "is_member_call": true, "source_file": "/private/tmp/mer/Game/WorldChunkFactory.swift", "source_location": "L98", "receiver": "rng"}, {"caller_nid": "private_tmp_mer_game_worldchunkfactory_worldchunkfactory_addcurrents", "callee": "nextCGFloat", "is_member_call": true, "source_file": "/private/tmp/mer/Game/WorldChunkFactory.swift", "source_location": "L99", "receiver": "rng"}, {"caller_nid": "private_tmp_mer_game_worldchunkfactory_worldchunkfactory_addcurrents", "callee": "nextCGFloat", "is_member_call": true, "source_file": "/private/tmp/mer/Game/WorldChunkFactory.swift", "source_location": "L102", "receiver": "rng"}, {"caller_nid": "private_tmp_mer_game_worldchunkfactory_worldchunkfactory_addcurrents", "callee": "nextCGFloat", "is_member_call": true, "source_file": "/private/tmp/mer/Game/WorldChunkFactory.swift", "source_location": "L103", "receiver": "rng"}, {"caller_nid": "private_tmp_mer_game_worldchunkfactory_worldchunkfactory_addcurrents", "callee": "addChild", "is_member_call": true, "source_file": "/private/tmp/mer/Game/WorldChunkFactory.swift", "source_location": "L105", "receiver": "node"}, {"caller_nid": "private_tmp_mer_game_worldchunkfactory_worldchunkfactory_addreefs", "callee": "seedForChunk", "is_member_call": true, "source_file": "/private/tmp/mer/Game/WorldChunkFactory.swift", "source_location": "L114", "receiver": "WorldSeed"}, {"caller_nid": "private_tmp_mer_game_worldchunkfactory_worldchunkfactory_addreefs", "callee": "Int", "is_member_call": false, "source_file": "/private/tmp/mer/Game/WorldChunkFactory.swift", "source_location": "L116", "receiver": null}, {"caller_nid": "private_tmp_mer_game_worldchunkfactory_worldchunkfactory_addreefs", "callee": "rounded", "is_member_call": true, "source_file": "/private/tmp/mer/Game/WorldChunkFactory.swift", "source_location": "L116", "receiver": null}, {"caller_nid": "private_tmp_mer_game_worldchunkfactory_worldchunkfactory_addreefs", "callee": "nextCGFloat", "is_member_call": true, "source_file": "/private/tmp/mer/Game/WorldChunkFactory.swift", "source_location": "L131", "receiver": "rng"}, {"caller_nid": "private_tmp_mer_game_worldchunkfactory_worldchunkfactory_addreefs", "callee": "setScale", "is_member_call": true, "source_file": "/private/tmp/mer/Game/WorldChunkFactory.swift", "source_location": "L142", "receiver": "cluster"}, {"caller_nid": "private_tmp_mer_game_worldchunkfactory_worldchunkfactory_addreefs", "callee": "addChild", "is_member_call": true, "source_file": "/private/tmp/mer/Game/WorldChunkFactory.swift", "source_location": "L143", "receiver": "node"}, {"caller_nid": "private_tmp_mer_game_worldchunkfactory_worldchunkfactory_addreefs", "callee": "append", "is_member_call": true, "source_file": "/private/tmp/mer/Game/WorldChunkFactory.swift", "source_location": "L144", "receiver": "placedClusters"}, {"caller_nid": "private_tmp_mer_game_worldchunkfactory_worldchunkfactory_reefclusterposition", "callee": "nextCGFloat", "is_member_call": true, "source_file": "/private/tmp/mer/Game/WorldChunkFactory.swift", "source_location": "L162", "receiver": "rng"}, {"caller_nid": "private_tmp_mer_game_worldchunkfactory_worldchunkfactory_reefclusterposition", "callee": "nextCGFloat", "is_member_call": true, "source_file": "/private/tmp/mer/Game/WorldChunkFactory.swift", "source_location": "L163", "receiver": "rng"}, {"caller_nid": "private_tmp_mer_game_worldchunkfactory_worldchunkfactory_reefclusterzposition", "callee": "clamped", "is_member_call": true, "source_file": "/private/tmp/mer/Game/WorldChunkFactory.swift", "source_location": "L193", "receiver": null}, {"caller_nid": "private_tmp_mer_game_worldchunkfactory_worldchunkfactory_reefclusterzposition", "callee": "nextCGFloat", "is_member_call": true, "source_file": "/private/tmp/mer/Game/WorldChunkFactory.swift", "source_location": "L194", "receiver": null}, {"caller_nid": "private_tmp_mer_game_worldchunkfactory_worldchunkfactory_addambientemitters", "callee": "seedForChunk", "is_member_call": true, "source_file": "/private/tmp/mer/Game/WorldChunkFactory.swift", "source_location": "L202", "receiver": "WorldSeed"}, {"caller_nid": "private_tmp_mer_game_worldchunkfactory_worldchunkfactory_addambientemitters", "callee": "SKEmitterNode", "is_member_call": false, "source_file": "/private/tmp/mer/Game/WorldChunkFactory.swift", "source_location": "L203", "receiver": null}, {"caller_nid": "private_tmp_mer_game_worldchunkfactory_worldchunkfactory_addambientemitters", "callee": "particleBirthRate", "is_member_call": true, "source_file": "/private/tmp/mer/Game/WorldChunkFactory.swift", "source_location": "L205", "receiver": "WorldVisualPalette"}, {"caller_nid": "private_tmp_mer_game_worldchunkfactory_worldchunkfactory_addambientemitters", "callee": "nextCGFloat", "is_member_call": true, "source_file": "/private/tmp/mer/Game/WorldChunkFactory.swift", "source_location": "L206", "receiver": "rng"}, {"caller_nid": "private_tmp_mer_game_worldchunkfactory_worldchunkfactory_addambientemitters", "callee": "CGVector", "is_member_call": false, "source_file": "/private/tmp/mer/Game/WorldChunkFactory.swift", "source_location": "L208", "receiver": null}, {"caller_nid": "private_tmp_mer_game_worldchunkfactory_worldchunkfactory_addambientemitters", "callee": "nextCGFloat", "is_member_call": true, "source_file": "/private/tmp/mer/Game/WorldChunkFactory.swift", "source_location": "L209", "receiver": "rng"}, {"caller_nid": "private_tmp_mer_game_worldchunkfactory_worldchunkfactory_addambientemitters", "callee": "nextCGFloat", "is_member_call": true, "source_file": "/private/tmp/mer/Game/WorldChunkFactory.swift", "source_location": "L213", "receiver": "rng"}, {"caller_nid": "private_tmp_mer_game_worldchunkfactory_worldchunkfactory_addambientemitters", "callee": "particleAlpha", "is_member_call": true, "source_file": "/private/tmp/mer/Game/WorldChunkFactory.swift", "source_location": "L215", "receiver": "WorldVisualPalette"}, {"caller_nid": "private_tmp_mer_game_worldchunkfactory_worldchunkfactory_addambientemitters", "callee": "particleColor", "is_member_call": true, "source_file": "/private/tmp/mer/Game/WorldChunkFactory.swift", "source_location": "L217", "receiver": "WorldVisualPalette"}, {"caller_nid": "private_tmp_mer_game_worldchunkfactory_worldchunkfactory_addambientemitters", "callee": "addChild", "is_member_call": true, "source_file": "/private/tmp/mer/Game/WorldChunkFactory.swift", "source_location": "L222", "receiver": "node"}, {"caller_nid": "private_tmp_mer_game_worldchunkfactory_worldchunkfactory_addambientemitters", "callee": "advanceSimulationTime", "is_member_call": true, "source_file": "/private/tmp/mer/Game/WorldChunkFactory.swift", "source_location": "L223", "receiver": "emitter"}, {"caller_nid": "private_tmp_mer_game_worldchunkfactory_worldchunkfactory_addambientemitters", "callee": "TimeInterval", "is_member_call": false, "source_file": "/private/tmp/mer/Game/WorldChunkFactory.swift", "source_location": "L223", "receiver": null}, {"caller_nid": "private_tmp_mer_game_worldchunkfactory_worldchunkfactory_makereefcluster", "callee": "nextCGFloat", "is_member_call": true, "source_file": "/private/tmp/mer/Game/WorldChunkFactory.swift", "source_location": "L232", "receiver": "rng"}, {"caller_nid": "private_tmp_mer_game_worldchunkfactory_worldchunkfactory_makereefcluster", "callee": "nextCGFloat", "is_member_call": true, "source_file": "/private/tmp/mer/Game/WorldChunkFactory.swift", "source_location": "L233", "receiver": "rng"}, {"caller_nid": "private_tmp_mer_game_worldchunkfactory_worldchunkfactory_makereefcluster", "callee": "nextCGFloat", "is_member_call": true, "source_file": "/private/tmp/mer/Game/WorldChunkFactory.swift", "source_location": "L237", "receiver": "rng"}, {"caller_nid": "private_tmp_mer_game_worldchunkfactory_worldchunkfactory_makereefcluster", "callee": "nextCGFloat", "is_member_call": true, "source_file": "/private/tmp/mer/Game/WorldChunkFactory.swift", "source_location": "L238", "receiver": "rng"}, {"caller_nid": "private_tmp_mer_game_worldchunkfactory_worldchunkfactory_makereefcluster", "callee": "addChild", "is_member_call": true, "source_file": "/private/tmp/mer/Game/WorldChunkFactory.swift", "source_location": "L240", "receiver": "cluster"}, {"caller_nid": "private_tmp_mer_game_worldchunkfactory_worldchunkfactory_makereefcluster", "callee": "nextCGFloat", "is_member_call": true, "source_file": "/private/tmp/mer/Game/WorldChunkFactory.swift", "source_location": "L244", "receiver": null}, {"caller_nid": "private_tmp_mer_game_worldchunkfactory_worldchunkfactory_makereefcluster", "callee": "nextCGFloat", "is_member_call": true, "source_file": "/private/tmp/mer/Game/WorldChunkFactory.swift", "source_location": "L245", "receiver": null}, {"caller_nid": "private_tmp_mer_game_worldchunkfactory_worldchunkfactory_makereefcluster", "callee": "addChild", "is_member_call": true, "source_file": "/private/tmp/mer/Game/WorldChunkFactory.swift", "source_location": "L247", "receiver": "cluster"}, {"caller_nid": "private_tmp_mer_game_worldchunkfactory_worldchunkfactory_makereefcluster", "callee": "chance", "is_member_call": true, "source_file": "/private/tmp/mer/Game/WorldChunkFactory.swift", "source_location": "L249", "receiver": "rng"}, {"caller_nid": "private_tmp_mer_game_worldchunkfactory_worldchunkfactory_makereefcluster", "callee": "nextCGFloat", "is_member_call": true, "source_file": "/private/tmp/mer/Game/WorldChunkFactory.swift", "source_location": "L250", "receiver": null}, {"caller_nid": "private_tmp_mer_game_worldchunkfactory_worldchunkfactory_makereefcluster", "callee": "nextCGFloat", "is_member_call": true, "source_file": "/private/tmp/mer/Game/WorldChunkFactory.swift", "source_location": "L251", "receiver": null}, {"caller_nid": "private_tmp_mer_game_worldchunkfactory_worldchunkfactory_makereefcluster", "callee": "chance", "is_member_call": true, "source_file": "/private/tmp/mer/Game/WorldChunkFactory.swift", "source_location": "L252", "receiver": "rng"}, {"caller_nid": "private_tmp_mer_game_worldchunkfactory_worldchunkfactory_makereefcluster", "callee": "nextCGFloat", "is_member_call": true, "source_file": "/private/tmp/mer/Game/WorldChunkFactory.swift", "source_location": "L257", "receiver": null}, {"caller_nid": "private_tmp_mer_game_worldchunkfactory_worldchunkfactory_makereefcluster", "callee": "nextCGFloat", "is_member_call": true, "source_file": "/private/tmp/mer/Game/WorldChunkFactory.swift", "source_location": "L258", "receiver": null}, {"caller_nid": "private_tmp_mer_game_worldchunkfactory_worldchunkfactory_makereefcluster", "callee": "nextCGFloat", "is_member_call": true, "source_file": "/private/tmp/mer/Game/WorldChunkFactory.swift", "source_location": "L259", "receiver": "rng"}, {"caller_nid": "private_tmp_mer_game_worldchunkfactory_worldchunkfactory_makereefcluster", "callee": "nextCGFloat", "is_member_call": true, "source_file": "/private/tmp/mer/Game/WorldChunkFactory.swift", "source_location": "L261", "receiver": "rng"}, {"caller_nid": "private_tmp_mer_game_worldchunkfactory_worldchunkfactory_makereefcluster", "callee": "addChild", "is_member_call": true, "source_file": "/private/tmp/mer/Game/WorldChunkFactory.swift", "source_location": "L262", "receiver": "cluster"}, {"caller_nid": "private_tmp_mer_game_worldchunkfactory_worldchunkfactory_makereefcluster", "callee": "chance", "is_member_call": true, "source_file": "/private/tmp/mer/Game/WorldChunkFactory.swift", "source_location": "L266", "receiver": "rng"}, {"caller_nid": "private_tmp_mer_game_worldchunkfactory_worldchunkfactory_makereefcluster", "callee": "nextCGFloat", "is_member_call": true, "source_file": "/private/tmp/mer/Game/WorldChunkFactory.swift", "source_location": "L269", "receiver": null}, {"caller_nid": "private_tmp_mer_game_worldchunkfactory_worldchunkfactory_makereefcluster", "callee": "nextCGFloat", "is_member_call": true, "source_file": "/private/tmp/mer/Game/WorldChunkFactory.swift", "source_location": "L270", "receiver": null}, {"caller_nid": "private_tmp_mer_game_worldchunkfactory_worldchunkfactory_makereefcluster", "callee": "addChild", "is_member_call": true, "source_file": "/private/tmp/mer/Game/WorldChunkFactory.swift", "source_location": "L273", "receiver": "cluster"}, {"caller_nid": "private_tmp_mer_game_worldchunkfactory_worldchunkfactory_makereefcluster", "callee": "plantSlotRange", "is_member_call": true, "source_file": "/private/tmp/mer/Game/WorldChunkFactory.swift", "source_location": "L277", "receiver": "profile"}, {"caller_nid": "private_tmp_mer_game_worldchunkfactory_worldchunkfactory_makereefcluster", "callee": "nextInt", "is_member_call": true, "source_file": "/private/tmp/mer/Game/WorldChunkFactory.swift", "source_location": "L278", "receiver": "rng"}, {"caller_nid": "private_tmp_mer_game_worldchunkfactory_worldchunkfactory_makereefcluster", "callee": "plantRule", "is_member_call": true, "source_file": "/private/tmp/mer/Game/WorldChunkFactory.swift", "source_location": "L280", "receiver": "profile"}, {"caller_nid": "private_tmp_mer_game_worldchunkfactory_worldchunkfactory_makereefcluster", "callee": "nextCGFloat", "is_member_call": true, "source_file": "/private/tmp/mer/Game/WorldChunkFactory.swift", "source_location": "L290", "receiver": "rng"}, {"caller_nid": "private_tmp_mer_game_worldchunkfactory_worldchunkfactory_makereefcluster", "callee": "addChild", "is_member_call": true, "source_file": "/private/tmp/mer/Game/WorldChunkFactory.swift", "source_location": "L291", "receiver": "cluster"}, {"caller_nid": "private_tmp_mer_game_worldchunkfactory_worldchunkfactory_makereefcluster", "callee": "detailSlotRange", "is_member_call": true, "source_file": "/private/tmp/mer/Game/WorldChunkFactory.swift", "source_location": "L294", "receiver": "profile"}, {"caller_nid": "private_tmp_mer_game_worldchunkfactory_worldchunkfactory_makereefcluster", "callee": "nextInt", "is_member_call": true, "source_file": "/private/tmp/mer/Game/WorldChunkFactory.swift", "source_location": "L295", "receiver": "rng"}, {"caller_nid": "private_tmp_mer_game_worldchunkfactory_worldchunkfactory_makereefcluster", "callee": "detailRule", "is_member_call": true, "source_file": "/private/tmp/mer/Game/WorldChunkFactory.swift", "source_location": "L297", "receiver": "profile"}, {"caller_nid": "private_tmp_mer_game_worldchunkfactory_worldchunkfactory_makereefcluster", "callee": "addChild", "is_member_call": true, "source_file": "/private/tmp/mer/Game/WorldChunkFactory.swift", "source_location": "L308", "receiver": "cluster"}, {"caller_nid": "private_tmp_mer_game_worldchunkfactory_worldchunkfactory_makerocksprite", "callee": "texture", "is_member_call": true, "source_file": "/private/tmp/mer/Game/WorldChunkFactory.swift", "source_location": "L320", "receiver": "WorldTextureCache"}, {"caller_nid": "private_tmp_mer_game_worldchunkfactory_worldchunkfactory_makerocksprite", "callee": "nextInt", "is_member_call": true, "source_file": "/private/tmp/mer/Game/WorldChunkFactory.swift", "source_location": "L323", "receiver": "rng"}, {"caller_nid": "private_tmp_mer_game_worldchunkfactory_worldchunkfactory_makereefskirtsprite", "callee": "texture", "is_member_call": true, "source_file": "/private/tmp/mer/Game/WorldChunkFactory.swift", "source_location": "L334", "receiver": "WorldTextureCache"}, {"caller_nid": "private_tmp_mer_game_worldchunkfactory_worldchunkfactory_makereefskirtsprite", "callee": "nextInt", "is_member_call": true, "source_file": "/private/tmp/mer/Game/WorldChunkFactory.swift", "source_location": "L337", "receiver": "rng"}, {"caller_nid": "private_tmp_mer_game_worldchunkfactory_worldchunkfactory_makereefskirtsprite", "callee": "nextCGFloat", "is_member_call": true, "source_file": "/private/tmp/mer/Game/WorldChunkFactory.swift", "source_location": "L339", "receiver": null}, {"caller_nid": "private_tmp_mer_game_worldchunkfactory_worldchunkfactory_makereefskirtsprite", "callee": "nextCGFloat", "is_member_call": true, "source_file": "/private/tmp/mer/Game/WorldChunkFactory.swift", "source_location": "L340", "receiver": null}, {"caller_nid": "private_tmp_mer_game_worldchunkfactory_worldchunkfactory_makereefskirtsprite", "callee": "nextCGFloat", "is_member_call": true, "source_file": "/private/tmp/mer/Game/WorldChunkFactory.swift", "source_location": "L342", "receiver": "rng"}, {"caller_nid": "private_tmp_mer_game_worldchunkfactory_worldchunkfactory_makekelpsprite", "callee": "nextCGFloat", "is_member_call": true, "source_file": "/private/tmp/mer/Game/WorldChunkFactory.swift", "source_location": "L351", "receiver": null}, {"caller_nid": "private_tmp_mer_game_worldchunkfactory_worldchunkfactory_makekelpsprite", "callee": "kelpHeight", "is_member_call": true, "source_file": "/private/tmp/mer/Game/WorldChunkFactory.swift", "source_location": "L351", "receiver": "WorldVisualPalette"}, {"caller_nid": "private_tmp_mer_game_worldchunkfactory_worldchunkfactory_makekelpsprite", "callee": "nextCGFloat", "is_member_call": true, "source_file": "/private/tmp/mer/Game/WorldChunkFactory.swift", "source_location": "L356", "receiver": "rng"}, {"caller_nid": "private_tmp_mer_game_worldchunkfactory_worldchunkfactory_makekelpsprite", "callee": "texture", "is_member_call": true, "source_file": "/private/tmp/mer/Game/WorldChunkFactory.swift", "source_location": "L365", "receiver": "WorldTextureCache"}, {"caller_nid": "private_tmp_mer_game_worldchunkfactory_worldchunkfactory_makekelpsprite", "callee": "nextInt", "is_member_call": true, "source_file": "/private/tmp/mer/Game/WorldChunkFactory.swift", "source_location": "L368", "receiver": "rng"}, {"caller_nid": "private_tmp_mer_game_worldchunkfactory_worldchunkfactory_makekelpsprite", "callee": "nextCGFloat", "is_member_call": true, "source_file": "/private/tmp/mer/Game/WorldChunkFactory.swift", "source_location": "L370", "receiver": null}, {"caller_nid": "private_tmp_mer_game_worldchunkfactory_worldchunkfactory_makekelpsprite", "callee": "nextCGFloat", "is_member_call": true, "source_file": "/private/tmp/mer/Game/WorldChunkFactory.swift", "source_location": "L374", "receiver": "rng"}, {"caller_nid": "private_tmp_mer_game_worldchunkfactory_worldchunkfactory_makekelpsprite", "callee": "nextCGFloat", "is_member_call": true, "source_file": "/private/tmp/mer/Game/WorldChunkFactory.swift", "source_location": "L375", "receiver": "rng"}, {"caller_nid": "private_tmp_mer_game_worldchunkfactory_worldchunkfactory_makekelpsprite", "callee": "chance", "is_member_call": true, "source_file": "/private/tmp/mer/Game/WorldChunkFactory.swift", "source_location": "L376", "receiver": "rng"}, {"caller_nid": "private_tmp_mer_game_worldchunkfactory_worldchunkfactory_makekelpsprite", "callee": "rotate", "is_member_call": true, "source_file": "/private/tmp/mer/Game/WorldChunkFactory.swift", "source_location": "L378", "receiver": "SKAction"}, {"caller_nid": "private_tmp_mer_game_worldchunkfactory_worldchunkfactory_makekelpsprite", "callee": "nextCGFloat", "is_member_call": true, "source_file": "/private/tmp/mer/Game/WorldChunkFactory.swift", "source_location": "L378", "receiver": null}, {"caller_nid": "private_tmp_mer_game_worldchunkfactory_worldchunkfactory_makekelpsprite", "callee": "TimeInterval", "is_member_call": false, "source_file": "/private/tmp/mer/Game/WorldChunkFactory.swift", "source_location": "L379", "receiver": null}, {"caller_nid": "private_tmp_mer_game_worldchunkfactory_worldchunkfactory_makekelpsprite", "callee": "nextCGFloat", "is_member_call": true, "source_file": "/private/tmp/mer/Game/WorldChunkFactory.swift", "source_location": "L379", "receiver": "rng"}, {"caller_nid": "private_tmp_mer_game_worldchunkfactory_worldchunkfactory_makekelpsprite", "callee": "rotate", "is_member_call": true, "source_file": "/private/tmp/mer/Game/WorldChunkFactory.swift", "source_location": "L380", "receiver": "SKAction"}, {"caller_nid": "private_tmp_mer_game_worldchunkfactory_worldchunkfactory_makekelpsprite", "callee": "nextCGFloat", "is_member_call": true, "source_file": "/private/tmp/mer/Game/WorldChunkFactory.swift", "source_location": "L380", "receiver": null}, {"caller_nid": "private_tmp_mer_game_worldchunkfactory_worldchunkfactory_makekelpsprite", "callee": "TimeInterval", "is_member_call": false, "source_file": "/private/tmp/mer/Game/WorldChunkFactory.swift", "source_location": "L381", "receiver": null}, {"caller_nid": "private_tmp_mer_game_worldchunkfactory_worldchunkfactory_makekelpsprite", "callee": "nextCGFloat", "is_member_call": true, "source_file": "/private/tmp/mer/Game/WorldChunkFactory.swift", "source_location": "L381", "receiver": "rng"}, {"caller_nid": "private_tmp_mer_game_worldchunkfactory_worldchunkfactory_makekelpsprite", "callee": "eaeInEaseOut", "is_member_call": true, "source_file": "/private/tmp/mer/Game/WorldChunkFactory.swift", "source_location": "L382", "receiver": "left"}, {"caller_nid": "private_tmp_mer_game_worldchunkfactory_worldchunkfactory_makekelpsprite", "callee": "eaeInEaseOut", "is_member_call": true, "source_file": "/private/tmp/mer/Game/WorldChunkFactory.swift", "source_location": "L383", "receiver": "right"}, {"caller_nid": "private_tmp_mer_game_worldchunkfactory_worldchunkfactory_makekelpsprite", "callee": "run", "is_member_call": true, "source_file": "/private/tmp/mer/Game/WorldChunkFactory.swift", "source_location": "L384", "receiver": "kelp"}, {"caller_nid": "private_tmp_mer_game_worldchunkfactory_worldchunkfactory_makedetailsprite", "callee": "texture", "is_member_call": true, "source_file": "/private/tmp/mer/Game/WorldChunkFactory.swift", "source_location": "L394", "receiver": "WorldTextureCache"}, {"caller_nid": "private_tmp_mer_game_worldchunkfactory_worldchunkfactory_makedetailsprite", "callee": "nextInt", "is_member_call": true, "source_file": "/private/tmp/mer/Game/WorldChunkFactory.swift", "source_location": "L397", "receiver": "rng"}, {"caller_nid": "private_tmp_mer_game_worldchunkfactory_worldchunkfactory_makedetailsprite", "callee": "nextCGFloat", "is_member_call": true, "source_file": "/private/tmp/mer/Game/WorldChunkFactory.swift", "source_location": "L402", "receiver": "rng"}, {"caller_nid": "private_tmp_mer_game_worldchunkfactory_worldchunkfactory_makedetailsprite", "callee": "nextCGFloat", "is_member_call": true, "source_file": "/private/tmp/mer/Game/WorldChunkFactory.swift", "source_location": "L403", "receiver": "rng"}, {"caller_nid": "private_tmp_mer_game_worldchunkfactory_worldchunkfactory_plantingx", "callee": "nextCGFloat", "is_member_call": true, "source_file": "/private/tmp/mer/Game/WorldChunkFactory.swift", "source_location": "L480", "receiver": "rng"}, {"caller_nid": "private_tmp_mer_game_worldchunkfactory_worldchunkfactory_plantingx", "callee": "nextCGFloat", "is_member_call": true, "source_file": "/private/tmp/mer/Game/WorldChunkFactory.swift", "source_location": "L482", "receiver": "rng"}, {"caller_nid": "private_tmp_mer_game_worldchunkfactory_worldchunkfactory_plantingsurfacey", "callee": "clamped", "is_member_call": true, "source_file": "/private/tmp/mer/Game/WorldChunkFactory.swift", "source_location": "L489", "receiver": null}, {"caller_nid": "private_tmp_mer_game_worldchunkfactory_worldchunkfactory_plantingsurfacey", "callee": "sin", "is_member_call": false, "source_file": "/private/tmp/mer/Game/WorldChunkFactory.swift", "source_location": "L491", "receiver": null}, {"caller_nid": "private_tmp_mer_game_worldchunkfactory_worldchunkfactory_plantingsurfacey", "callee": "nextCGFloat", "is_member_call": true, "source_file": "/private/tmp/mer/Game/WorldChunkFactory.swift", "source_location": "L492", "receiver": "rng"}, {"caller_nid": "private_tmp_mer_game_worldchunkfactory_worldchunkfactory_plantingsurfacey", "callee": "clamped", "is_member_call": true, "source_file": "/private/tmp/mer/Game/WorldChunkFactory.swift", "source_location": "L494", "receiver": "y"}, {"caller_nid": "private_tmp_mer_game_worldchunkfactory_worldchunkfactory_rootsink", "callee": "nextCGFloat", "is_member_call": true, "source_file": "/private/tmp/mer/Game/WorldChunkFactory.swift", "source_location": "L499", "receiver": null}, {"caller_nid": "private_tmp_mer_game_worldchunkfactory_worldchunkfactory_detailsize", "callee": "nextCGFloat", "is_member_call": true, "source_file": "/private/tmp/mer/Game/WorldChunkFactory.swift", "source_location": "L531", "receiver": "rng"}, {"caller_nid": "private_tmp_mer_game_worldchunkfactory_worldchunkfactory_detailsize", "callee": "nextCGFloat", "is_member_call": true, "source_file": "/private/tmp/mer/Game/WorldChunkFactory.swift", "source_location": "L532", "receiver": "rng"}, {"caller_nid": "private_tmp_mer_game_worldchunkfactory_worldchunkfactory_detailsize", "callee": "nextCGFloat", "is_member_call": true, "source_file": "/private/tmp/mer/Game/WorldChunkFactory.swift", "source_location": "L534", "receiver": "rng"}, {"caller_nid": "private_tmp_mer_game_worldchunkfactory_worldchunkfactory_detailsize", "callee": "nextCGFloat", "is_member_call": true, "source_file": "/private/tmp/mer/Game/WorldChunkFactory.swift", "source_location": "L535", "receiver": "rng"}, {"caller_nid": "private_tmp_mer_game_worldchunkfactory_worldchunkfactory_detailsize", "callee": "nextCGFloat", "is_member_call": true, "source_file": "/private/tmp/mer/Game/WorldChunkFactory.swift", "source_location": "L537", "receiver": "rng"}, {"caller_nid": "private_tmp_mer_game_worldchunkfactory_worldchunkfactory_detailsize", "callee": "nextCGFloat", "is_member_call": true, "source_file": "/private/tmp/mer/Game/WorldChunkFactory.swift", "source_location": "L538", "receiver": "rng"}, {"caller_nid": "private_tmp_mer_game_worldchunkfactory_worldchunkfactory_detailsize", "callee": "nextCGFloat", "is_member_call": true, "source_file": "/private/tmp/mer/Game/WorldChunkFactory.swift", "source_location": "L540", "receiver": "rng"}, {"caller_nid": "private_tmp_mer_game_worldchunkfactory_worldchunkfactory_detailsize", "callee": "nextCGFloat", "is_member_call": true, "source_file": "/private/tmp/mer/Game/WorldChunkFactory.swift", "source_location": "L541", "receiver": "rng"}, {"caller_nid": "private_tmp_mer_game_worldchunkfactory_worldchunkfactory_detailsize", "callee": "nextCGFloat", "is_member_call": true, "source_file": "/private/tmp/mer/Game/WorldChunkFactory.swift", "source_location": "L544", "receiver": "rng"}, {"caller_nid": "private_tmp_mer_game_worldchunkfactory_worldchunkfactory_detailsize", "callee": "nextCGFloat", "is_member_call": true, "source_file": "/private/tmp/mer/Game/WorldChunkFactory.swift", "source_location": "L545", "receiver": "rng"}, {"caller_nid": "private_tmp_mer_game_worldchunkfactory_worldchunkfactory_detailsize", "callee": "nextCGFloat", "is_member_call": true, "source_file": "/private/tmp/mer/Game/WorldChunkFactory.swift", "source_location": "L547", "receiver": "rng"}, {"caller_nid": "private_tmp_mer_game_worldchunkfactory_worldchunkfactory_detailsize", "callee": "nextCGFloat", "is_member_call": true, "source_file": "/private/tmp/mer/Game/WorldChunkFactory.swift", "source_location": "L548", "receiver": "rng"}, {"caller_nid": "private_tmp_mer_game_worldchunkfactory_worldchunkfactory_detailsize", "callee": "nextCGFloat", "is_member_call": true, "source_file": "/private/tmp/mer/Game/WorldChunkFactory.swift", "source_location": "L550", "receiver": "rng"}, {"caller_nid": "private_tmp_mer_game_worldchunkfactory_worldchunkfactory_detailsize", "callee": "nextCGFloat", "is_member_call": true, "source_file": "/private/tmp/mer/Game/WorldChunkFactory.swift", "source_location": "L551", "receiver": "rng"}, {"caller_nid": "private_tmp_mer_game_worldchunkfactory_worldchunkfactory_detailsize", "callee": "nextCGFloat", "is_member_call": true, "source_file": "/private/tmp/mer/Game/WorldChunkFactory.swift", "source_location": "L553", "receiver": "rng"}, {"caller_nid": "private_tmp_mer_game_worldchunkfactory_worldchunkfactory_detailsize", "callee": "nextCGFloat", "is_member_call": true, "source_file": "/private/tmp/mer/Game/WorldChunkFactory.swift", "source_location": "L554", "receiver": "rng"}, {"caller_nid": "private_tmp_mer_game_worldchunkfactory_worldchunkfactory_reefdensity", "callee": "isDepthCompatible", "is_member_call": true, "source_file": "/private/tmp/mer/Game/WorldChunkFactory.swift", "source_location": "L562", "receiver": "profile"}, {"caller_nid": "private_tmp_mer_game_worldchunkfactory_worldchunkfactory_reefdensity", "callee": "clamped", "is_member_call": true, "source_file": "/private/tmp/mer/Game/WorldChunkFactory.swift", "source_location": "L593", "receiver": null}, {"caller_nid": "private_tmp_mer_game_worldchunkfactory_worldchunkfactory_reefdensity", "callee": "nextCGFloat", "is_member_call": true, "source_file": "/private/tmp/mer/Game/WorldChunkFactory.swift", "source_location": "L593", "receiver": null}, {"caller_nid": "private_tmp_mer_game_worldchunkfactory_worldchunkfactory_reefdensity", "callee": "reefDensityBias", "is_member_call": true, "source_file": "/private/tmp/mer/Game/WorldChunkFactory.swift", "source_location": "L593", "receiver": null}, {"caller_nid": "private_tmp_mer_game_worldchunkfactory_worldchunkfactory_randompoint", "callee": "nextCGFloat", "is_member_call": true, "source_file": "/private/tmp/mer/Game/WorldChunkFactory.swift", "source_location": "L600", "receiver": "rng"}, {"caller_nid": "private_tmp_mer_game_worldchunkfactory_worldchunkfactory_randompoint", "callee": "nextCGFloat", "is_member_call": true, "source_file": "/private/tmp/mer/Game/WorldChunkFactory.swift", "source_location": "L601", "receiver": "rng"}], "swift_type_table": {"path": "/private/tmp/mer/Game/WorldChunkFactory.swift", "table": {"node": "SKNode", "terrainFootprint": "CGSize", "position": "CGPoint", "scale": "CGFloat", "coord": "WorldChunkCoord", "profile": "EcosystemBiomeProfile", "includeAmbientEmitters": "Bool", "zone": "DepthZone", "biome": "AquaticBiome", "cluster": "ReefCluster", "rect": "CGRect", "placedClusters": "PlacedReefCluster", "rng": "SeededGenerator", "y": "CGFloat", "size": "CGSize", "baseSize": "CGSize", "kind": "WorldStampKind", "rule": "EcosystemVegetationRule", "sprite": "SKSpriteNode", "localX": "CGFloat", "margin": "CGFloat", "ribbon": "SKSpriteNode", "count": "Int", "emitter": "SKEmitterNode", "shelfSize": "CGSize", "rock": "SKSpriteNode", "skirt": "SKSpriteNode", "kelp": "SKSpriteNode", "detail": "SKSpriteNode"}}}